{
  "generated_at": "2026-07-17T22:32:28.804022+08:00",
  "total_titles_processed": 2152,
  "failed_sources": [],
  "trends": [
    {
      "keyword_group": "美股 A股 港股 大A 恒生科技 创业板 科创板",
      "match_count": 110,
      "titles": [
        {
          "title": "半导体抛售潮拖累美股，纳指100一度跌2%，中概再逆市涨，黄金大跌破4000",
          "url": "https://wallstreetcn.com/articles/3777075",
          "source": "华尔街见闻",
          "ranks": [
            1,
            2
          ],
          "is_new": false,
          "appearance_count": 20,
          "time_info": "[08时19分 ~ 22时32分]"
        },
        {
          "title": "美PPI确认通胀降温，科技巨头力撑美股指两连阳，中概股大涨，美光、闪迪暴跌8%",
          "url": "https://wallstreetcn.com/articles/3776964",
          "source": "华尔街见闻",
          "ranks": [
            5
          ],
          "is_new": false,
          "appearance_count": 9,
          "time_info": "[00时27分 ~ 06时19分]"
        },
        {
          "title": "半导体抛售潮重创全球股市，美股盘初涨跌互现，存储股普跌，台积电跌3%，现货黄金跌2%",
          "url": "https://wallstreetcn.com/articles/3777075",
          "source": "华尔街见闻",
          "ranks": [
            1
          ],
          "is_new": false,
          "appearance_count": 8,
          "time_info": "[00时27分 ~ 05时20分]"
        },
        {
          "title": "美股收盘：芯片股持续下挫拖累纳指跌近1.5% 存储、光通信板块领跌",
          "url": "https://www.cls.cn/detail/2428956",
          "source": "财联社热门",
          "ranks": [
            11,
            5,
            4,
            3
          ],
          "is_new": false,
          "appearance_count": 9,
          "time_info": "[06时19分 ~ 14时44分]"
        },
        {
          "title": "7月17日投资避雷针：美股半导体板块再度大跌 SK海力士、闪迪跌超12%",
          "url": "https://www.cls.cn/detail/2429026",
          "source": "财联社热门",
          "ranks": [
            10,
            7,
            8,
            5,
            4
          ],
          "is_new": false,
          "appearance_count": 11,
          "time_info": "[09时31分 ~ 16时41分]"
        },
        {
          "title": "财联社、科创板日报记者探营WAIC 2026：从超节点算力到进厂机器人 AI与物理世界开启“无界融合”",
          "url": "https://www.cls.cn/detail/2428882",
          "source": "财联社热门",
          "ranks": [
            10,
            6,
            3,
            2
          ],
          "is_new": false,
          "appearance_count": 8,
          "time_info": "[08时19分 ~ 14时44分]"
        },
        {
          "title": "美股期指走低 纳指期货跌1% 芯片股普遍承压 | 今夜看点",
          "url": "https://www.cls.cn/detail/2428765",
          "source": "财联社热门",
          "ranks": [
            7,
            8,
            6
          ],
          "is_new": false,
          "appearance_count": 15,
          "time_info": "[00时27分 ~ 12时04分]"
        },
        {
          "title": "外资机构把脉A股：AI景气度仍向好，市场正进入结构性分化新阶段",
          "url": "https://m.thepaper.cn/newsDetail_forward_33586841",
          "source": "澎湃新闻",
          "ranks": [
            9,
            10,
            7
          ],
          "is_new": false,
          "appearance_count": 10,
          "time_info": "[00时27分 ~ 08时19分]"
        },
        {
          "title": "30家科创板公司中报预喜：22家净利润增长，6家扭亏为盈",
          "url": "https://m.thepaper.cn/newsDetail_forward_33600948",
          "source": "澎湃新闻",
          "ranks": [
            19,
            18,
            17,
            16,
            15,
            14,
            12,
            11
          ],
          "is_new": false,
          "appearance_count": 13,
          "time_info": "[13时51分 ~ 22时32分]"
        },
        {
          "title": "百度申请香港、纳斯达克双重主要上市，有望赶上9月港股通调整窗口",
          "url": "https://m.thepaper.cn/newsDetail_forward_33598176",
          "source": "澎湃新闻",
          "ranks": [
            20,
            19,
            16,
            17,
            15,
            14,
            13
          ],
          "is_new": false,
          "appearance_count": 22,
          "time_info": "[00时27分 ~ 17时33分]"
        },
        {
          "title": "【每日收评】创业板与科创50指数双双跌超7%，全市场近200股跌停，科技权重集体退潮",
          "url": "https://www.cls.cn/detail/2429589",
          "source": "财联社热门",
          "ranks": [
            5,
            6,
            7,
            8
          ],
          "is_new": false,
          "appearance_count": 8,
          "time_info": "[17时33分 ~ 22时32分]"
        },
        {
          "title": "A股今天暴跌原因",
          "url": "https://s.weibo.com/weibo?q=%23A%E8%82%A1%E4%BB%8A%E5%A4%A9%E6%9A%B4%E8%B7%8C%E5%8E%9F%E5%9B%A0%23&t=31&band_rank=22&Refer=top",
          "source": "微博",
          "ranks": [
            22,
            11,
            12,
            18,
            17
          ],
          "is_new": false,
          "appearance_count": 8,
          "time_info": "[17时33分 ~ 22时32分]"
        },
        {
          "title": "A股",
          "url": "https://s.weibo.com/weibo?q=A%E8%82%A1&t=31&band_rank=29&Refer=top",
          "source": "微博",
          "ranks": [
            29,
            12,
            15,
            18
          ],
          "is_new": false,
          "appearance_count": 8,
          "time_info": "[11时01分 ~ 16时41分]"
        },
        {
          "title": "沪指失守3800点，电力银行逆势拉升，创业板、科创50跌逾7%，医药芯片深度回调，港股AI大模型股智谱跌近30%",
          "url": "https://wallstreetcn.com/articles/3777165",
          "source": "华尔街见闻",
          "ranks": [
            10,
            9,
            8
          ],
          "is_new": false,
          "appearance_count": 7,
          "time_info": "[18时32分 ~ 22时32分]"
        },
        {
          "title": "A股杀跌是中期调整还是牛市结束",
          "url": "https://www.toutiao.com/trending/7663417152111644223/",
          "source": "今日头条",
          "ranks": [
            12,
            8,
            10
          ],
          "is_new": false,
          "appearance_count": 7,
          "time_info": "[18时32分 ~ 22时32分]"
        },
        {
          "title": "【焦点复盘】创业板指录得周线四连阴，全市场超640股跌逾10%，电力板块逆势活跃",
          "url": "https://www.cls.cn/detail/2429653",
          "source": "财联社热门",
          "ranks": [
            12,
            11,
            10
          ],
          "is_new": false,
          "appearance_count": 7,
          "time_info": "[18时32分 ~ 22时32分]"
        },
        {
          "title": "A股",
          "url": "https://www.douyin.com/hot/2574308",
          "source": "抖音",
          "ranks": [
            11
          ],
          "is_new": false,
          "appearance_count": 7,
          "time_info": "[11时01分 ~ 15时38分]"
        },
        {
          "title": "A股哪些板块在逆势吸筹",
          "url": "https://www.toutiao.com/trending/7663116917388873259/",
          "source": "今日头条",
          "ranks": [
            2,
            9,
            19
          ],
          "is_new": false,
          "appearance_count": 5,
          "time_info": "[00时27分 ~ 03时26分]"
        },
        {
          "title": "A股突然放量释放何信号",
          "url": "https://www.toutiao.com/trending/7663326159165197865/",
          "source": "今日头条",
          "ranks": [
            1
          ],
          "is_new": false,
          "appearance_count": 1,
          "time_info": "13时51分"
        },
        {
          "title": "A股怎么了",
          "url": "https://www.baidu.com/s?wd=A%E8%82%A1%E6%80%8E%E4%B9%88%E4%BA%86",
          "source": "百度热搜",
          "ranks": [
            1
          ],
          "is_new": false,
          "appearance_count": 1,
          "time_info": "17时33分"
        },
        {
          "title": "半导体抛售潮拖累美股，纳指跌超1%，中概再度逆市收涨，黄金跌破4000关口",
          "url": "https://wallstreetcn.com/articles/3777075",
          "source": "华尔街见闻",
          "ranks": [
            1
          ],
          "is_new": false,
          "appearance_count": 1,
          "time_info": "06时19分"
        },
        {
          "title": "A股贵金属板块重挫，赤峰黄金跌超9%，兴业银锡、招金黄金、中金黄金、西部黄金等跟跌。",
          "url": "https://flash.jin10.com/detail/20260717103455837800",
          "source": "金十数据",
          "ranks": [
            1
          ],
          "is_new": false,
          "appearance_count": 1,
          "time_info": "11时02分"
        },
        {
          "title": "恒指日内跌近2%，恒生科技指数跌超4%，恒生生物科技指数跌6.7%。智谱跌超22%，MINIMAX跌超13%。",
          "url": "https://wallstreetcn.com/livenews/3135456",
          "source": "华尔街见闻-快讯",
          "ranks": [
            1
          ],
          "is_new": false,
          "appearance_count": 1,
          "time_info": "12时04分"
        },
        {
          "title": "A股",
          "url": "https://www.baidu.com/s?wd=A%E8%82%A1",
          "source": "百度热搜",
          "ranks": [
            19,
            10,
            12
          ],
          "is_new": false,
          "appearance_count": 6,
          "time_info": "[14时44分 ~ 17时33分]"
        },
        {
          "title": "美联储两大官员放鹰：关注通胀风险，支持适度加息；美军连续第六晚对伊朗采取打击行动，伊朗部分机场、桥梁和铁路枢纽遭袭……当前现货金银、美油维持卖出信号，美股信号分化，后市情绪如何？欢迎前往“数据库-嘉盛市场晴雨表”查看并订阅（数据每10分钟更新1次）。",
          "url": "https://flash.jin10.com/detail/20260717103419821800",
          "source": "金十数据",
          "ranks": [
            2
          ],
          "is_new": false,
          "appearance_count": 1,
          "time_info": "11时02分"
        },
        {
          "title": "上证综指日内大跌3%，深证成指跌5.65%，创业板指跌7.48%。",
          "url": "https://flash.jin10.com/detail/20260717133944145800",
          "source": "金十数据",
          "ranks": [
            2
          ],
          "is_new": false,
          "appearance_count": 1,
          "time_info": "13时51分"
        },
        {
          "title": "百胜餐饮集团美股盘后下跌4%，美国食品药品监督管理局（FDA）将就塔可钟（Taco Bell）的生菜问题发布警告。",
          "url": "https://wallstreetcn.com/livenews/3135298",
          "source": "华尔街见闻-快讯",
          "ranks": [
            2
          ],
          "is_new": false,
          "appearance_count": 1,
          "time_info": "06时19分"
        },
        {
          "title": "道指转涨，刷新日高、逼近52560点，美股盘初一度跌至51986.74点刷新日低。 存储板块集体拉升，纷纷收复此前4%-7%的盘初跌幅。SK海力士ADR目前涨4.63%，美光科技股价下跌0.17%，闪迪股价上涨0.28%。",
          "url": "https://wallstreetcn.com/livenews/3135778",
          "source": "华尔街见闻-快讯",
          "ranks": [
            2
          ],
          "is_new": true,
          "appearance_count": 1,
          "time_info": "22时32分"
        },
        {
          "title": "科技股抛售潮蔓延，美股低开，纳指跌1.8%，半导体板块领跌，布油涨3%，黄金失守4000美元",
          "url": "https://wallstreetcn.com/articles/3777186",
          "source": "华尔街见闻",
          "ranks": [
            3
          ],
          "is_new": true,
          "appearance_count": 1,
          "time_info": "22时32分"
        },
        {
          "title": "多只宽基ETF显著放量 创业板ETF易方达（159915）成交额超昨日全天",
          "url": "https://wallstreetcn.com/livenews/3135450",
          "source": "华尔街见闻-快讯",
          "ranks": [
            4
          ],
          "is_new": false,
          "appearance_count": 1,
          "time_info": "12时04分"
        },
        {
          "title": "美股盘初，主要行业ETF涨跌不一，半导体ETF跌2.5%，全球科技股指数ETF跌近2%，能源业ETF、日常消费品ETF涨超1%。",
          "url": "https://wallstreetcn.com/livenews/3135775",
          "source": "华尔街见闻-快讯",
          "ranks": [
            4
          ],
          "is_new": true,
          "appearance_count": 1,
          "time_info": "22时32分"
        },
        {
          "title": "A股半日放量1219亿调整",
          "url": "https://s.weibo.com/weibo?q=%23A%E8%82%A1%E5%8D%8A%E6%97%A5%E6%94%BE%E9%87%8F1219%E4%BA%BF%E8%B0%83%E6%95%B4%23&t=31&band_rank=5&Refer=top",
          "source": "微博",
          "ranks": [
            5,
            10,
            23
          ],
          "is_new": false,
          "appearance_count": 4,
          "time_info": "[13时51分 ~ 15时38分]"
        },
        {
          "title": "A股中际旭创成交额达500亿元，现跌7.91%。",
          "url": "https://flash.jin10.com/detail/20260717142643898800",
          "source": "金十数据",
          "ranks": [
            5
          ],
          "is_new": false,
          "appearance_count": 1,
          "time_info": "14时44分"
        },
        {
          "title": "上证指数早盘收报3818.59点，跌1.64%。 深证成指早盘收报13953.26点，跌3.70%。 创业板指早盘收报3518.65点，跌4.71%。 沪深300早盘收报4583.23点，跌2.45%。 科创50早盘收报1763.22点，跌4.53%。 中证500早盘收报7691.88点，跌3.32%。 中证1000早盘收报7392.22点，跌3.14%。",
          "url": "https://wallstreetcn.com/livenews/3135449",
          "source": "华尔街见闻-快讯",
          "ranks": [
            5
          ],
          "is_new": false,
          "appearance_count": 1,
          "time_info": "12时04分"
        },
        {
          "title": "美股盘前，存储芯片股普跌，闪迪跌约6%，纳斯达克100指数期货跌1.8%",
          "url": "https://wallstreetcn.com/livenews/3135572",
          "source": "华尔街见闻-快讯",
          "ranks": [
            5
          ],
          "is_new": false,
          "appearance_count": 1,
          "time_info": "16时41分"
        },
        {
          "title": "周五美股盘前你需要了解的全球要闻",
          "url": "https://wallstreetcn.com/livenews/3135728",
          "source": "华尔街见闻-快讯",
          "ranks": [
            5
          ],
          "is_new": false,
          "appearance_count": 1,
          "time_info": "21时32分"
        },
        {
          "title": "美股芯片股深夜大跌",
          "url": "https://www.toutiao.com/trending/7663271539885739558/",
          "source": "今日头条",
          "ranks": [
            27,
            9,
            21
          ],
          "is_new": false,
          "appearance_count": 5,
          "time_info": "[08时19分 ~ 11时02分]"
        },
        {
          "title": "创业板指跌幅扩大至8%，上证指数跌3.35%，深证成指跌6.03%。新易盛盘中跌15.02%，现报461.10元。",
          "url": "https://wallstreetcn.com/livenews/3135504",
          "source": "华尔街见闻-快讯",
          "ranks": [
            1,
            14,
            30
          ],
          "is_new": false,
          "appearance_count": 3,
          "time_info": "[13时51分 ~ 15时38分]"
        },
        {
          "title": "中际旭创港股上市获中国证监会备案",
          "url": "https://wallstreetcn.com/livenews/3135665",
          "source": "华尔街见闻-快讯",
          "ranks": [
            1,
            15,
            29
          ],
          "is_new": false,
          "appearance_count": 3,
          "time_info": "[18时32分 ~ 20时23分]"
        },
        {
          "title": "美股期货走低，标普500指数期货跌0.3%，纳斯达克100指数期货跌0.6%。",
          "url": "https://wallstreetcn.com/livenews/3135338",
          "source": "华尔街见闻-快讯",
          "ranks": [
            1,
            22
          ],
          "is_new": false,
          "appearance_count": 2,
          "time_info": "[08时19分 ~ 09时32分]"
        },
        {
          "title": "UBS将交通银行A股评级从中性上调至买进，目标价8.10元人民币。",
          "url": "https://wallstreetcn.com/livenews/3135581",
          "source": "华尔街见闻-快讯",
          "ranks": [
            1,
            29
          ],
          "is_new": false,
          "appearance_count": 2,
          "time_info": "[16时41分 ~ 17时33分]"
        },
        {
          "title": "恒生指数收盘跌1.78%，恒生科技指数跌4.37%",
          "url": "https://wallstreetcn.com/livenews/3135578",
          "source": "华尔街见闻-快讯",
          "ranks": [
            2,
            30
          ],
          "is_new": false,
          "appearance_count": 2,
          "time_info": "[16时41分 ~ 17时33分]"
        },
        {
          "title": "A股正迎来年内难得的黄金买点",
          "url": "https://s.weibo.com/weibo?q=%23A%E8%82%A1%E6%AD%A3%E8%BF%8E%E6%9D%A5%E5%B9%B4%E5%86%85%E9%9A%BE%E5%BE%97%E7%9A%84%E9%BB%84%E9%87%91%E4%B9%B0%E7%82%B9%23&t=31&band_rank=6&Refer=top",
          "source": "微博",
          "ranks": [
            6,
            8,
            27
          ],
          "is_new": false,
          "appearance_count": 4,
          "time_info": "[16时40分 ~ 18时32分]"
        },
        {
          "title": "创业板指跌超5%，沪指跌1.52%，深成指跌3.7%，医药医疗、算力硬件、半导体芯片等方向跌幅居前，沪深京三市下跌个股近4500只，其中近170股跌超9%。",
          "url": "https://wallstreetcn.com/livenews/3135424",
          "source": "华尔街见闻-快讯",
          "ranks": [
            3,
            23
          ],
          "is_new": false,
          "appearance_count": 2,
          "time_info": "[11时02分 ~ 12时04分]"
        },
        {
          "title": "美股存储芯片指数收跌超8%",
          "url": "https://wallstreetcn.com/livenews/3135275",
          "source": "华尔街见闻-快讯",
          "ranks": [
            4,
            21
          ],
          "is_new": false,
          "appearance_count": 2,
          "time_info": "[05时20分 ~ 06时19分]"
        },
        {
          "title": "峰哥称不再点评A股",
          "url": "https://s.weibo.com/weibo?q=%E5%B3%B0%E5%93%A5%E7%A7%B0%E4%B8%8D%E5%86%8D%E7%82%B9%E8%AF%84A%E8%82%A1&t=31&band_rank=8&Refer=top",
          "source": "微博",
          "ranks": [
            8,
            24
          ],
          "is_new": false,
          "appearance_count": 4,
          "time_info": "[15时37分 ~ 16时41分]"
        },
        {
          "title": "创业板指跌超7%。",
          "url": "https://wallstreetcn.com/livenews/3135497",
          "source": "华尔街见闻-快讯",
          "ranks": [
            5,
            18
          ],
          "is_new": false,
          "appearance_count": 2,
          "time_info": "[13时51分 ~ 14时44分]"
        },
        {
          "title": "A股收盘：创业板指跌超7%，全市场近200股跌停",
          "url": "https://wallstreetcn.com/livenews/3135544",
          "source": "华尔街见闻-快讯",
          "ranks": [
            5,
            28
          ],
          "is_new": false,
          "appearance_count": 2,
          "time_info": "[15时38分 ~ 16时41分]"
        },
        {
          "title": "A股重磅信号！多只宽基ETF，显著放量！大资金再度出手？",
          "url": "https://wallstreetcn.com/articles/3777184",
          "source": "华尔街见闻",
          "ranks": [
            10
          ],
          "is_new": false,
          "appearance_count": 4,
          "time_info": "[20时23分 ~ 22时32分]"
        },
        {
          "title": "创业板大跌引满仓抄底",
          "url": "https://s.weibo.com/weibo?q=%E5%88%9B%E4%B8%9A%E6%9D%BF%E5%A4%A7%E8%B7%8C%E5%BC%95%E6%BB%A1%E4%BB%93%E6%8A%84%E5%BA%95&t=31&band_rank=13&Refer=top",
          "source": "微博",
          "ranks": [
            13,
            29
          ],
          "is_new": false,
          "appearance_count": 4,
          "time_info": "[17时33分 ~ 19时28分]"
        },
        {
          "title": "巴菲特怒斥美股投机狂热",
          "url": "https://search.bilibili.com/all?keyword=%E5%B7%B4%E8%8F%B2%E7%89%B9%E6%80%92%E6%96%A5%E7%BE%8E%E8%82%A1%E6%8A%95%E6%9C%BA%E7%8B%82%E7%83%AD",
          "source": "bilibili 热搜",
          "ranks": [
            8,
            24
          ],
          "is_new": false,
          "appearance_count": 3,
          "time_info": "[09时31分 ~ 12时04分]"
        },
        {
          "title": "A股黄金买点来了吗",
          "url": "https://www.toutiao.com/trending/7663454627538406938/",
          "source": "今日头条",
          "ranks": [
            14,
            16
          ],
          "is_new": false,
          "appearance_count": 3,
          "time_info": "[21时31分 ~ 22时32分]"
        },
        {
          "title": "A股长期来看还要创新高",
          "url": "https://s.weibo.com/weibo?q=%23A%E8%82%A1%E9%95%BF%E6%9C%9F%E6%9D%A5%E7%9C%8B%E8%BF%98%E8%A6%81%E5%88%9B%E6%96%B0%E9%AB%98%23&t=31&band_rank=22&Refer=top",
          "source": "微博",
          "ranks": [
            22,
            18
          ],
          "is_new": false,
          "appearance_count": 3,
          "time_info": "[11时01分 ~ 12时04分]"
        },
        {
          "title": "A股年内最强无差别杀跌",
          "url": "https://s.weibo.com/weibo?q=%23A%E8%82%A1%E5%B9%B4%E5%86%85%E6%9C%80%E5%BC%BA%E6%97%A0%E5%B7%AE%E5%88%AB%E6%9D%80%E8%B7%8C%23&t=31&band_rank=27&Refer=top",
          "source": "微博",
          "ranks": [
            27,
            28
          ],
          "is_new": false,
          "appearance_count": 3,
          "time_info": "[21时31分 ~ 22时32分]"
        },
        {
          "title": "A股券商股异动拉升，湘财股份直线涨停，国盛证券涨超5%，天风证券、第一创业、东方财富、华创云信跟涨。",
          "url": "https://wallstreetcn.com/livenews/3135420",
          "source": "华尔街见闻-快讯",
          "ranks": [
            6,
            27
          ],
          "is_new": false,
          "appearance_count": 2,
          "time_info": "[11时02分 ~ 12时04分]"
        },
        {
          "title": "美股存储芯片指数跌幅扩大至7%，闪迪跌幅扩大至10%，西部数据跌近9%。SK海力士ADR跌8.6%。费城半导体指数目前跌3.5%，纳斯达克100指数维持超过0.9%的跌幅。",
          "url": "https://wallstreetcn.com/livenews/3135181",
          "source": "华尔街见闻-快讯",
          "ranks": [
            7,
            23
          ],
          "is_new": false,
          "appearance_count": 2,
          "time_info": "[00时28分 ~ 01时28分]"
        },
        {
          "title": "沪指跌幅缩窄至2%以内，深证成指跌幅收窄至4%，创业板指跌4.76%。",
          "url": "https://wallstreetcn.com/livenews/3135516",
          "source": "华尔街见闻-快讯",
          "ranks": [
            7,
            23
          ],
          "is_new": false,
          "appearance_count": 2,
          "time_info": "[14时44分 ~ 15时38分]"
        },
        {
          "title": "上证指数收报3764.15点，跌3.05%。 深证成指收报13706.88点，跌5.40%。 创业板指收报3428.63点，跌7.15%。 沪深300收报4529.10点，跌3.60%。 科创50收报1715.40点，跌7.12%。 中证500收报7513.76点，跌5.55%。 中证1000收报7168.00点，跌6.08%。",
          "url": "https://wallstreetcn.com/livenews/3135542",
          "source": "华尔街见闻-快讯",
          "ranks": [
            7,
            30
          ],
          "is_new": false,
          "appearance_count": 2,
          "time_info": "[15时38分 ~ 16时41分]"
        },
        {
          "title": "年内科创板公司新增计划回购金额上限超80亿",
          "url": "https://wallstreetcn.com/livenews/3135697",
          "source": "华尔街见闻-快讯",
          "ranks": [
            7,
            28
          ],
          "is_new": false,
          "appearance_count": 2,
          "time_info": "[20时23分 ~ 21时32分]"
        },
        {
          "title": "恒生科技指数午后跌幅扩大至5%，恒生指数跌超2%，智谱跌超26%，MINIMAX跌超14%。",
          "url": "https://wallstreetcn.com/livenews/3135491",
          "source": "华尔街见闻-快讯",
          "ranks": [
            8,
            21
          ],
          "is_new": false,
          "appearance_count": 2,
          "time_info": "[13时51分 ~ 14时44分]"
        },
        {
          "title": "A股创新药概念跌势扩大，百奥赛图、百诚医药20cm跌停，药康生物、泓博医药、前沿生物、华纳药厂等多股跌超10%。",
          "url": "https://wallstreetcn.com/livenews/3135490",
          "source": "华尔街见闻-快讯",
          "ranks": [
            9,
            22
          ],
          "is_new": false,
          "appearance_count": 2,
          "time_info": "[13时51分 ~ 14时44分]"
        },
        {
          "title": "美股大类资产类ETF普遍下跌，新兴市场收跌2.1%，与黄金ETF、可转债ETF领跌",
          "url": "https://wallstreetcn.com/livenews/3135268",
          "source": "华尔街见闻-快讯",
          "ranks": [
            10,
            28
          ],
          "is_new": false,
          "appearance_count": 2,
          "time_info": "[05时20分 ~ 06时19分]"
        },
        {
          "title": "创业板指、科创50指数午后跌超6%，兆易创新触及跌停，成交额237.98亿元，沪深京三市下跌个股超4600只。",
          "url": "https://wallstreetcn.com/livenews/3135489",
          "source": "华尔街见闻-快讯",
          "ranks": [
            10,
            23
          ],
          "is_new": false,
          "appearance_count": 2,
          "time_info": "[13时51分 ~ 14时44分]"
        },
        {
          "title": "周四（7月16日），美股行业ETF多数收涨，区域银行ETF涨2.82%，日常消费品ETF、银行业ETF至少涨2.44%。 网络股指数ETF则收跌1.54%，科技行业ETF跌2.24%，全球科技股指数ETF跌2.47%，半导体ETF跌3.70%。",
          "url": "https://wallstreetcn.com/livenews/3135267",
          "source": "华尔街见闻-快讯",
          "ranks": [
            11,
            29
          ],
          "is_new": false,
          "appearance_count": 2,
          "time_info": "[05时20分 ~ 06时19分]"
        },
        {
          "title": "A股跌至3790点",
          "url": "https://s.weibo.com/weibo?q=%23A%E8%82%A1%E8%B7%8C%E8%87%B33790%E7%82%B9%23&t=31&band_rank=12&Refer=top",
          "source": "微博",
          "ranks": [
            12
          ],
          "is_new": false,
          "appearance_count": 2,
          "time_info": "[15时37分 ~ 15时38分]"
        },
        {
          "title": "【午后宽基ETF持续放量 3只ETF成交额超100亿】午后宽基ETF成交额持续放大，创业板ETF易方达（159915）、科创50ETF华夏（588000）、沪深300ETF华泰柏瑞（510300）成交额突破100亿，中证1000ETF南方（512100）、中证500ETF南方（510500）、A500ETF华泰柏瑞（563360）、A500ETF南方（159352）、创业板50ETF华安（159949）成交额均已超昨日全天。",
          "url": "https://wallstreetcn.com/livenews/3135508",
          "source": "华尔街见闻-快讯",
          "ranks": [
            12,
            28
          ],
          "is_new": false,
          "appearance_count": 2,
          "time_info": "[14时44分 ~ 15时38分]"
        },
        {
          "title": "创业板指跌幅扩大至7%",
          "url": "https://flash.jin10.com/detail/20260717133618841800",
          "source": "金十数据",
          "ranks": [
            6
          ],
          "is_new": false,
          "appearance_count": 1,
          "time_info": "13时51分"
        },
        {
          "title": "7月17日午间收评：创业板指半日跌4.71%，全市场下跌个股近4400只",
          "url": "https://wallstreetcn.com/livenews/3135448",
          "source": "华尔街见闻-快讯",
          "ranks": [
            6
          ],
          "is_new": false,
          "appearance_count": 1,
          "time_info": "12时04分"
        },
        {
          "title": "A股芯片产业链局部回暖，有研硅涨超10%，长电科技直线拉升一度涨超8%，华虹宏力、拓荆科技、燕东微、中微公司等冲高。",
          "url": "https://flash.jin10.com/detail/20260717142230904800",
          "source": "金十数据",
          "ranks": [
            8
          ],
          "is_new": false,
          "appearance_count": 1,
          "time_info": "14时44分"
        },
        {
          "title": "长鑫科技打新开启：科创板史上最大IPO，中一签能赚多少？",
          "url": "https://wallstreetcn.com/articles/3777100",
          "source": "华尔街见闻",
          "ranks": [
            9
          ],
          "is_new": false,
          "appearance_count": 1,
          "time_info": "08时19分"
        },
        {
          "title": "美股期货下跌 半导体抛售加剧推动投资者转向其他板块",
          "url": "https://flash.jin10.com/detail/20260717162337933800",
          "source": "金十数据",
          "ranks": [
            9
          ],
          "is_new": false,
          "appearance_count": 1,
          "time_info": "16时41分"
        },
        {
          "title": "交银国际给予兆易创新A股买进的初始评级，目标价798元人民币。",
          "url": "https://wallstreetcn.com/livenews/3135414",
          "source": "华尔街见闻-快讯",
          "ranks": [
            10
          ],
          "is_new": false,
          "appearance_count": 1,
          "time_info": "11时02分"
        },
        {
          "title": "A股氟化工概念板块短线拉升，中巨芯涨超10%，联创股份、闰土股份、中欣氟材、雅克科技、金宏气体等跟涨。",
          "url": "https://flash.jin10.com/detail/20260717103053427800",
          "source": "金十数据",
          "ranks": [
            11
          ],
          "is_new": false,
          "appearance_count": 1,
          "time_info": "11时02分"
        },
        {
          "title": "金十数据整理：A股盘前市场要闻速递（2026-07-17）",
          "url": "https://flash.jin10.com/detail/20260717090420903800",
          "source": "金十数据",
          "ranks": [
            12
          ],
          "is_new": false,
          "appearance_count": 1,
          "time_info": "09时32分"
        },
        {
          "title": "恒生科技指数日内跌超3%，智谱跌超15%，MINIMAX跌10%。",
          "url": "https://wallstreetcn.com/livenews/3135412",
          "source": "华尔街见闻-快讯",
          "ranks": [
            12
          ],
          "is_new": false,
          "appearance_count": 1,
          "time_info": "11时02分"
        },
        {
          "title": "科创50、创业板指跌逾6%",
          "url": "https://www.baidu.com/s?wd=%E7%A7%91%E5%88%9B50%E3%80%81%E5%88%9B%E4%B8%9A%E6%9D%BF%E6%8C%87%E8%B7%8C%E9%80%BE6%25",
          "source": "百度热搜",
          "ranks": [
            13
          ],
          "is_new": false,
          "appearance_count": 1,
          "time_info": "13时51分"
        },
        {
          "title": "陈果：A股正迎来年内难得黄金买点",
          "url": "https://www.baidu.com/s?wd=%E9%99%88%E6%9E%9C%EF%BC%9AA%E8%82%A1%E6%AD%A3%E8%BF%8E%E6%9D%A5%E5%B9%B4%E5%86%85%E9%9A%BE%E5%BE%97%E9%BB%84%E9%87%91%E4%B9%B0%E7%82%B9",
          "source": "百度热搜",
          "ranks": [
            13
          ],
          "is_new": false,
          "appearance_count": 1,
          "time_info": "17时33分"
        },
        {
          "title": "华尔街机构：散户影响力空前提升 美股交易格局正在重塑",
          "url": "https://www.cls.cn/detail/2428851",
          "source": "财联社热门",
          "ranks": [
            13
          ],
          "is_new": false,
          "appearance_count": 1,
          "time_info": "12时04分"
        },
        {
          "title": "金十数据整理：A股每日市场要闻回顾（2026-07-17）",
          "url": "https://flash.jin10.com/detail/20260717152117792800",
          "source": "金十数据",
          "ranks": [
            13
          ],
          "is_new": false,
          "appearance_count": 1,
          "time_info": "15时38分"
        },
        {
          "title": "恒生科技指数跌幅扩大3%，小鹏集团(09868.HK)跌近7%，快手(01024.HK)、美团(03690.HK)跌超5%。",
          "url": "https://flash.jin10.com/detail/20260717102714241800",
          "source": "金十数据",
          "ranks": [
            14
          ],
          "is_new": false,
          "appearance_count": 1,
          "time_info": "11时02分"
        },
        {
          "title": "SK海力士美股股价收复逾4%跌幅，现涨超1%。",
          "url": "https://wallstreetcn.com/livenews/3135764",
          "source": "华尔街见闻-快讯",
          "ranks": [
            14
          ],
          "is_new": true,
          "appearance_count": 1,
          "time_info": "22时32分"
        },
        {
          "title": "金十图示：2026年07月16日（周四）美股热门股票行情一览（美股收盘）",
          "url": "https://flash.jin10.com/detail/20260717040547992800",
          "source": "金十数据",
          "ranks": [
            15
          ],
          "is_new": false,
          "appearance_count": 1,
          "time_info": "05时20分"
        },
        {
          "title": "金十数据整理：每日港股市场要闻速递（2026-07-17）",
          "url": "https://flash.jin10.com/detail/20260717090222852800",
          "source": "金十数据",
          "ranks": [
            15
          ],
          "is_new": false,
          "appearance_count": 1,
          "time_info": "09时32分"
        },
        {
          "title": "A股午评：三大股低开低走 CRO、CPO概念早盘重挫",
          "url": "https://flash.jin10.com/detail/20260717113221851800",
          "source": "金十数据",
          "ranks": [
            15
          ],
          "is_new": false,
          "appearance_count": 1,
          "time_info": "12时04分"
        },
        {
          "title": "奈飞二季度营收125.6亿美元，分析师预期125.8亿美元。 二季度每股收益（EPS）为0.80美元，分析师预期0.79美元。 预计全年营收510亿-514亿美元，公司原本预计507亿-517亿美元。 预计三季度营收128.6亿美元，分析师预期130亿美元。 预计三季度EPS为0.82美元，分析师预期0.84美元。 “我们观看了啥”（What we Watched）的发布频率将从半年一次降低至一年一次。 奈飞美股盘后跌3%。",
          "url": "https://wallstreetcn.com/livenews/3135263",
          "source": "华尔街见闻-快讯",
          "ranks": [
            15
          ],
          "is_new": false,
          "appearance_count": 1,
          "time_info": "05时20分"
        },
        {
          "title": "业内人士：当前A股市场调整更多是慢牛中的高波动，市场当前位置具备较强支撑",
          "url": "https://wallstreetcn.com/livenews/3135526",
          "source": "华尔街见闻-快讯",
          "ranks": [
            15
          ],
          "is_new": false,
          "appearance_count": 1,
          "time_info": "15时38分"
        },
        {
          "title": "恒生指数主连夜盘收跌0.29%，报24917点。 恒生科技指数主连夜盘收跌0.31%，报4815点。",
          "url": "https://wallstreetcn.com/livenews/3135239",
          "source": "华尔街见闻-快讯",
          "ranks": [
            16
          ],
          "is_new": false,
          "appearance_count": 1,
          "time_info": "04时17分"
        },
        {
          "title": "刘纪鹏谈A股长慢牛的底层逻辑",
          "url": "https://www.toutiao.com/trending/7663297022048341547/",
          "source": "今日头条",
          "ranks": [
            17
          ],
          "is_new": false,
          "appearance_count": 1,
          "time_info": "12时04分"
        },
        {
          "title": "金十图示：2026年07月16日（周四）热门中概股行情一览（美股收盘）",
          "url": "https://flash.jin10.com/detail/20260717040536324800",
          "source": "金十数据",
          "ranks": [
            18
          ],
          "is_new": false,
          "appearance_count": 1,
          "time_info": "05时20分"
        },
        {
          "title": "港股收评：恒生科技指数收跌4.37% AI、生物技术、半导体概念大挫",
          "url": "https://flash.jin10.com/detail/20260717161426733800",
          "source": "金十数据",
          "ranks": [
            18
          ],
          "is_new": false,
          "appearance_count": 1,
          "time_info": "16时41分"
        },
        {
          "title": "金十数据整理：每日美股市场要闻速递（2026-07-17）",
          "url": "https://flash.jin10.com/detail/20260717211106193800",
          "source": "金十数据",
          "ranks": [
            18
          ],
          "is_new": false,
          "appearance_count": 1,
          "time_info": "21时32分"
        },
        {
          "title": "多只宽基ETF显著放量 创业板ETF易方达(159915)成交额超昨日全天",
          "url": "https://flash.jin10.com/detail/20260717113105633800",
          "source": "金十数据",
          "ranks": [
            19
          ],
          "is_new": false,
          "appearance_count": 1,
          "time_info": "12时04分"
        },
        {
          "title": "动量崩塌、美股随时都会绷不住？“大空头”盯上港股便宜筹码",
          "url": "https://flash.jin10.com/detail/20260717161406074800",
          "source": "金十数据",
          "ranks": [
            19
          ],
          "is_new": false,
          "appearance_count": 1,
          "time_info": "16时41分"
        },
        {
          "title": "港股南方两倍做多三星电子跌超20%，南方两倍做多海力士跌超18%。",
          "url": "https://wallstreetcn.com/livenews/3135430",
          "source": "华尔街见闻-快讯",
          "ranks": [
            19
          ],
          "is_new": false,
          "appearance_count": 1,
          "time_info": "12时04分"
        },
        {
          "title": "创业板指跌破3500点，日内跌5.3%。",
          "url": "https://wallstreetcn.com/livenews/3135428",
          "source": "华尔街见闻-快讯",
          "ranks": [
            20
          ],
          "is_new": false,
          "appearance_count": 1,
          "time_info": "12时04分"
        },
        {
          "title": "香港恒生指数7月17日（周五）收盘下跌446.36点，跌幅1.78%，报24562.24点；<br/>香港恒生科技指数7月17日（周五）收盘下跌211.27点，跌幅4.37%，报4623.17点；<br/>国企指数7月17日（周五）收盘下跌181.41点，跌幅2.18%，报8136.73点；<br/>红筹指数7月17日（周五）收盘下跌27.84点，跌幅0.7%，报3963.54点。",
          "url": "https://flash.jin10.com/detail/20260717161138440800",
          "source": "金十数据",
          "ranks": [
            21
          ],
          "is_new": false,
          "appearance_count": 1,
          "time_info": "16时41分"
        },
        {
          "title": "恒生科技指数跌幅扩大至4%，恒生指数现跌1.88%。",
          "url": "https://flash.jin10.com/detail/20260717112840876800",
          "source": "金十数据",
          "ranks": [
            22
          ],
          "is_new": false,
          "appearance_count": 1,
          "time_info": "12时04分"
        },
        {
          "title": "美股收盘：三大股指收跌 SK海力士跌13%",
          "url": "https://flash.jin10.com/detail/20260717040125271800",
          "source": "金十数据",
          "ranks": [
            23
          ],
          "is_new": false,
          "appearance_count": 1,
          "time_info": "05时20分"
        },
        {
          "title": "恒生科技指数午后跌幅扩大至5%，恒生指数现跌2.36%，智谱(02513.HK)跌26.81%，MINIMAX-W(00100.HK)跌14.3%。",
          "url": "https://flash.jin10.com/detail/20260717131949000800",
          "source": "金十数据",
          "ranks": [
            23
          ],
          "is_new": false,
          "appearance_count": 1,
          "time_info": "13时51分"
        },
        {
          "title": "美股半导体重挫传导亚洲，亚洲科技链为何集体失血？",
          "url": "https://flash.jin10.com/detail/20260717085429155800",
          "source": "金十数据",
          "ranks": [
            24
          ],
          "is_new": false,
          "appearance_count": 1,
          "time_info": "09时32分"
        },
        {
          "title": "美股盘初：纳指跌1.8%，费城半导体指数跌超3%，奈飞跌约12%，SpaceX跌约3%",
          "url": "https://wallstreetcn.com/livenews/3135751",
          "source": "华尔街见闻-快讯",
          "ranks": [
            24
          ],
          "is_new": true,
          "appearance_count": 1,
          "time_info": "22时32分"
        },
        {
          "title": "创业板指日内重挫6%，深证成指跌4.6%，上证综指跌4.6%。",
          "url": "https://flash.jin10.com/detail/20260717131601600800",
          "source": "金十数据",
          "ranks": [
            25
          ],
          "is_new": false,
          "appearance_count": 1,
          "time_info": "13时51分"
        },
        {
          "title": "港股收盘，恒生指数收跌1.78%，恒生科技指数收跌4.37%，智谱(02513.HK)全日收跌28.49%，MINIMAX-W(00100.HK)跌15.63%。",
          "url": "https://flash.jin10.com/detail/20260717160850053800",
          "source": "金十数据",
          "ranks": [
            25
          ],
          "is_new": false,
          "appearance_count": 1,
          "time_info": "16时41分"
        },
        {
          "title": "恒生科技指数跌超2%，MINIMAX跌幅扩大至7.4%，小鹏集团、蔚来跌超5%。",
          "url": "https://wallstreetcn.com/livenews/3135388",
          "source": "华尔街见闻-快讯",
          "ranks": [
            25
          ],
          "is_new": false,
          "appearance_count": 1,
          "time_info": "11时02分"
        },
        {
          "title": "A股三大股指短线回暖，上证综指跌幅缩窄至2%以内，深证成指跌幅缩窄至4%，创业板指现跌4.76%。",
          "url": "https://flash.jin10.com/detail/20260717140954756800",
          "source": "金十数据",
          "ranks": [
            26
          ],
          "is_new": false,
          "appearance_count": 1,
          "time_info": "14时44分"
        },
        {
          "title": "美股期货跌幅扩大， 纳斯达克100指数期货跌2%，标普500指数期货跌1%，道指期货跌0.6%。",
          "url": "https://wallstreetcn.com/livenews/3135586",
          "source": "华尔街见闻-快讯",
          "ranks": [
            26
          ],
          "is_new": false,
          "appearance_count": 1,
          "time_info": "17时33分"
        },
        {
          "title": "证监会同意高凯技术科创板IPO注册",
          "url": "https://wallstreetcn.com/livenews/3135626",
          "source": "华尔街见闻-快讯",
          "ranks": [
            26
          ],
          "is_new": false,
          "appearance_count": 1,
          "time_info": "18时32分"
        },
        {
          "title": "中际旭创或成港股年内最大IPO",
          "url": "https://wallstreetcn.com/livenews/3135742",
          "source": "华尔街见闻-快讯",
          "ranks": [
            28
          ],
          "is_new": true,
          "appearance_count": 1,
          "time_info": "22时32分"
        },
        {
          "title": "恒生科技指数日内跌幅扩大至1%。",
          "url": "https://wallstreetcn.com/livenews/3135378",
          "source": "华尔街见闻-快讯",
          "ranks": [
            29
          ],
          "is_new": false,
          "appearance_count": 1,
          "time_info": "11时02分"
        },
        {
          "title": "创业板指、科创50均跌超4%，算力硬件、半导体芯片等方向跌幅居前，沪深京三市下跌个股近2700只。",
          "url": "https://wallstreetcn.com/livenews/3135376",
          "source": "华尔街见闻-快讯",
          "ranks": [
            30
          ],
          "is_new": false,
          "appearance_count": 1,
          "time_info": "11时02分"
        }
      ]
    },
    {
      "keyword_group": "特朗普",
      "match_count": 45,
      "titles": [
        {
          "title": "中方驳斥特朗普“中国干预美国大选”论调",
          "url": "https://news.ifeng.com/c/8upog6XKRmu",
          "source": "凤凰网",
          "ranks": [
            1
          ],
          "is_new": false,
          "appearance_count": 10,
          "time_info": "[16时40分 ~ 22时32分]"
        },
        {
          "title": "白宫：特朗普将出席世界杯决赛",
          "url": "https://news.ifeng.com/c/8upEtP2Gcyf",
          "source": "凤凰网",
          "ranks": [
            1,
            2,
            3
          ],
          "is_new": false,
          "appearance_count": 19,
          "time_info": "[09时31分 ~ 22时32分]"
        },
        {
          "title": "担心特朗普全国演讲乱说话，共和党人：我们被吓得“屁滚尿流”",
          "url": "https://news.ifeng.com/c/8uoXl1Ao0h2",
          "source": "凤凰网",
          "ranks": [
            5,
            4
          ],
          "is_new": false,
          "appearance_count": 12,
          "time_info": "[00时27分 ~ 09时32分]"
        },
        {
          "title": "特朗普：我们47年前就应该攻击伊朗，那样会容易得多",
          "url": "https://m.thepaper.cn/newsDetail_forward_33598128",
          "source": "澎湃新闻",
          "ranks": [
            14,
            15,
            17,
            13,
            12,
            11
          ],
          "is_new": false,
          "appearance_count": 12,
          "time_info": "[09时31分 ~ 17时33分]"
        },
        {
          "title": "美国首例！特朗普恼火：可怕的决定，要输给中国了",
          "url": "https://news.ifeng.com/c/8uofMrB5Gdq",
          "source": "凤凰网",
          "ranks": [
            1,
            2
          ],
          "is_new": false,
          "appearance_count": 3,
          "time_info": "[08时19分 ~ 09时32分]"
        },
        {
          "title": "白宫：美国总统特朗普明天（当地时间周五）将前往纽约。",
          "url": "https://flash.jin10.com/detail/20260717012223455800",
          "source": "金十数据",
          "ranks": [
            1
          ],
          "is_new": false,
          "appearance_count": 1,
          "time_info": "01时28分"
        },
        {
          "title": "白宫：特朗普今晚（北京时间今早9点）发表讲话时将谈及伊朗问题。",
          "url": "https://flash.jin10.com/detail/20260717015332023800",
          "source": "金十数据",
          "ranks": [
            1
          ],
          "is_new": false,
          "appearance_count": 1,
          "time_info": "02时21分"
        },
        {
          "title": "白宫：美国总统特朗普将出席世界杯决赛。",
          "url": "https://flash.jin10.com/detail/20260717012138949800",
          "source": "金十数据",
          "ranks": [
            2
          ],
          "is_new": false,
          "appearance_count": 1,
          "time_info": "01时28分"
        },
        {
          "title": "美国白宫通讯总监‌张振熙：懦夫。NBC和ABC不想让你听到真相。他们只想对你隐瞒事实。（此前报道称这两家媒体将不会电视直播特朗普今天黄金时段的演讲）",
          "url": "https://flash.jin10.com/detail/20260717074910149800",
          "source": "金十数据",
          "ranks": [
            2
          ],
          "is_new": false,
          "appearance_count": 1,
          "time_info": "08时19分"
        },
        {
          "title": "美国总统特朗普：很快就会看到我们在伊朗取得胜利的成果。",
          "url": "https://flash.jin10.com/detail/20260717090854707800",
          "source": "金十数据",
          "ranks": [
            2
          ],
          "is_new": false,
          "appearance_count": 1,
          "time_info": "09时32分"
        },
        {
          "title": "美国总统特朗普：立即解密有关选举的情报。",
          "url": "https://flash.jin10.com/detail/20260717090843511800",
          "source": "金十数据",
          "ranks": [
            3
          ],
          "is_new": false,
          "appearance_count": 1,
          "time_info": "09时32分"
        },
        {
          "title": "美国总统特朗普：我们拥有世界上最强大的军队。美国在伊朗问题上占据上风。",
          "url": "https://flash.jin10.com/detail/20260717090653215800",
          "source": "金十数据",
          "ranks": [
            4
          ],
          "is_new": false,
          "appearance_count": 1,
          "time_info": "09时32分"
        },
        {
          "title": "特朗普：很快就会看到在伊朗的成果。",
          "url": "https://wallstreetcn.com/livenews/3135354",
          "source": "华尔街见闻-快讯",
          "ranks": [
            5
          ],
          "is_new": false,
          "appearance_count": 1,
          "time_info": "09时32分"
        },
        {
          "title": "白宫再曝内幕交易丑闻！特朗普御用提词员利用演讲信息牟利遭调查",
          "url": "https://www.cls.cn/detail/2429184",
          "source": "财联社热门",
          "ranks": [
            13,
            12
          ],
          "is_new": false,
          "appearance_count": 5,
          "time_info": "[15时37分 ~ 17时33分]"
        },
        {
          "title": "美国总统特朗普准备在（今天稍早的）演讲中谈论委内瑞拉大选。（Semafor）",
          "url": "https://wallstreetcn.com/livenews/3135274",
          "source": "华尔街见闻-快讯",
          "ranks": [
            5,
            22
          ],
          "is_new": false,
          "appearance_count": 2,
          "time_info": "[05时20分 ~ 06时19分]"
        },
        {
          "title": "特朗普说别人都在笑话美国",
          "url": "https://search.bilibili.com/all?keyword=%E7%89%B9%E6%9C%97%E6%99%AE%E8%AF%B4%E5%88%AB%E4%BA%BA%E9%83%BD%E5%9C%A8%E7%AC%91%E8%AF%9D%E7%BE%8E%E5%9B%BD",
          "source": "bilibili 热搜",
          "ranks": [
            7
          ],
          "is_new": false,
          "appearance_count": 2,
          "time_info": "[15时37分 ~ 15时38分]"
        },
        {
          "title": "白宫新闻秘书Leavitt：白宫提词器操作员被停职。 美国总统特朗普认为，被控参与下注的提词器操作员“行为可耻”。",
          "url": "https://wallstreetcn.com/livenews/3135212",
          "source": "华尔街见闻-快讯",
          "ranks": [
            7,
            24
          ],
          "is_new": false,
          "appearance_count": 2,
          "time_info": "[02时21分 ~ 03时26分]"
        },
        {
          "title": "据CBS：美国总统特朗普将于当地时间7月22日访问亚特兰大都会区一所高中，推广新的“特朗普账户”投资计划。",
          "url": "https://flash.jin10.com/detail/20260717024018004800",
          "source": "金十数据",
          "ranks": [
            13,
            19
          ],
          "is_new": false,
          "appearance_count": 2,
          "time_info": "[03时26分 ~ 04时17分]"
        },
        {
          "title": "白宫官宣特朗普将出席世界杯决赛",
          "url": "https://www.toutiao.com/trending/7663253128728657971/",
          "source": "今日头条",
          "ranks": [
            16,
            23
          ],
          "is_new": false,
          "appearance_count": 2,
          "time_info": "[12时04分 ~ 13时51分]"
        },
        {
          "title": "白宫：特朗普总统始终愿意进行外交谈判。",
          "url": "https://flash.jin10.com/detail/20260717014747492800",
          "source": "金十数据",
          "ranks": [
            7
          ],
          "is_new": false,
          "appearance_count": 1,
          "time_info": "02时21分"
        },
        {
          "title": "美国总统特朗普：美国边境变得更加安全。",
          "url": "https://flash.jin10.com/detail/20260717090559742800",
          "source": "金十数据",
          "ranks": [
            7
          ],
          "is_new": false,
          "appearance_count": 1,
          "time_info": "09时32分"
        },
        {
          "title": "美国总统特朗普向全国发表讲话。特朗普宣扬通胀下降和股市上涨。",
          "url": "https://wallstreetcn.com/livenews/3135352",
          "source": "华尔街见闻-快讯",
          "ranks": [
            7
          ],
          "is_new": false,
          "appearance_count": 1,
          "time_info": "09时32分"
        },
        {
          "title": "白宫：特朗普总统与副总统万斯在伊朗冲突问题上意见一致。",
          "url": "https://flash.jin10.com/detail/20260717014735582800",
          "source": "金十数据",
          "ranks": [
            8
          ],
          "is_new": false,
          "appearance_count": 1,
          "time_info": "02时21分"
        },
        {
          "title": "美国总统特朗普：我们的投资规模创历史新高，股市表现也处于最佳状态。",
          "url": "https://flash.jin10.com/detail/20260717090517561800",
          "source": "金十数据",
          "ranks": [
            8
          ],
          "is_new": false,
          "appearance_count": 1,
          "time_info": "09时32分"
        },
        {
          "title": "白宫：（关于以色列内部有人试图让战争无限持续）特朗普总统认同外国势力会试图影响美国公众舆论，这是一个客观事实。",
          "url": "https://flash.jin10.com/detail/20260717014701100800",
          "source": "金十数据",
          "ranks": [
            9
          ],
          "is_new": false,
          "appearance_count": 1,
          "time_info": "02时21分"
        },
        {
          "title": "美国总统特朗普：美国通胀创六年来最大降幅。",
          "url": "https://flash.jin10.com/detail/20260717090454225800",
          "source": "金十数据",
          "ranks": [
            9
          ],
          "is_new": false,
          "appearance_count": 1,
          "time_info": "09时32分"
        },
        {
          "title": "白宫：特朗普总统不会允许伊朗在霍尔木兹海峡发动袭击而不付出代价。美国可以在任何时间、任何地点打击伊朗。",
          "url": "https://flash.jin10.com/detail/20260717014539254800",
          "source": "金十数据",
          "ranks": [
            10
          ],
          "is_new": false,
          "appearance_count": 1,
          "time_info": "02时21分"
        },
        {
          "title": "美国总统特朗普：我们目前在美国的投资规模是有史以来最大的。",
          "url": "https://flash.jin10.com/detail/20260717090442505800",
          "source": "金十数据",
          "ranks": [
            10
          ],
          "is_new": false,
          "appearance_count": 1,
          "time_info": "09时32分"
        },
        {
          "title": "白宫新闻秘书Leavitt：美国总统特朗普今晚将谈论选举诚信。 重申（特朗普）对沃尔玛的赞赏。 特朗普将前往世界杯决赛现场。",
          "url": "https://wallstreetcn.com/livenews/3135209",
          "source": "华尔街见闻-快讯",
          "ranks": [
            10
          ],
          "is_new": false,
          "appearance_count": 1,
          "time_info": "02时21分"
        },
        {
          "title": "新闻蒸馏器︱特朗普倾向扩大对伊朗军事行动，导弹已击中争议岛",
          "url": "https://m.thepaper.cn/newsDetail_forward_33596311",
          "source": "澎湃新闻",
          "ranks": [
            11
          ],
          "is_new": false,
          "appearance_count": 1,
          "time_info": "12时04分"
        },
        {
          "title": "美国总统特朗普：我们的国家比以往任何时候都更安全。",
          "url": "https://flash.jin10.com/detail/20260717090429637800",
          "source": "金十数据",
          "ranks": [
            11
          ],
          "is_new": false,
          "appearance_count": 1,
          "time_info": "09时32分"
        },
        {
          "title": "美国商品期货交易委员会（CFTC）：提词器操作员在预测平台Kalshi上就特朗普的发言内容下注，CFTC正在调查。",
          "url": "https://wallstreetcn.com/livenews/3135177",
          "source": "华尔街见闻-快讯",
          "ranks": [
            11
          ],
          "is_new": false,
          "appearance_count": 1,
          "time_info": "00时28分"
        },
        {
          "title": "特朗普：别人都在笑话美国",
          "url": "https://wallstreetcn.com/livenews/3135439",
          "source": "华尔街见闻-快讯",
          "ranks": [
            11
          ],
          "is_new": false,
          "appearance_count": 1,
          "time_info": "12时04分"
        },
        {
          "title": "美国总统特朗普：我们现在是世界上最棒的国家。",
          "url": "https://flash.jin10.com/detail/20260717090356263800",
          "source": "金十数据",
          "ranks": [
            13
          ],
          "is_new": false,
          "appearance_count": 1,
          "time_info": "09时32分"
        },
        {
          "title": "万斯驳斥特朗普亲信利用内幕获利传言",
          "url": "https://flash.jin10.com/detail/20260717072923735800",
          "source": "金十数据",
          "ranks": [
            15
          ],
          "is_new": false,
          "appearance_count": 1,
          "time_info": "08时19分"
        },
        {
          "title": "伊朗称特朗普关于美国囚犯获释的说法不实",
          "url": "https://wallstreetcn.com/livenews/3135237",
          "source": "华尔街见闻-快讯",
          "ranks": [
            18
          ],
          "is_new": false,
          "appearance_count": 1,
          "time_info": "04时17分"
        },
        {
          "title": "特朗普说别人都笑话美国",
          "url": "https://s.weibo.com/weibo?q=%23%E7%89%B9%E6%9C%97%E6%99%AE%E8%AF%B4%E5%88%AB%E4%BA%BA%E9%83%BD%E7%AC%91%E8%AF%9D%E7%BE%8E%E5%9B%BD%23&t=31&band_rank=20&Refer=top",
          "source": "微博",
          "ranks": [
            20
          ],
          "is_new": false,
          "appearance_count": 1,
          "time_info": "17时33分"
        },
        {
          "title": "白宫提词员利用特朗普演讲内幕获利逾10万美元，CFTC对其展开调查",
          "url": "https://flash.jin10.com/detail/20260717010030245800",
          "source": "金十数据",
          "ranks": [
            21
          ],
          "is_new": false,
          "appearance_count": 1,
          "time_info": "01时28分"
        },
        {
          "title": "特朗普将赴世界杯现场观看决赛",
          "url": "https://flash.jin10.com/detail/20260717021058975800",
          "source": "金十数据",
          "ranks": [
            25
          ],
          "is_new": false,
          "appearance_count": 1,
          "time_info": "03时26分"
        },
        {
          "title": "美国总统特朗普：昨晚我的演讲获得了很好的评价，观众人数众多。请通过《拯救美国法案》！",
          "url": "https://flash.jin10.com/detail/20260717195445964800",
          "source": "金十数据",
          "ranks": [
            26
          ],
          "is_new": false,
          "appearance_count": 1,
          "time_info": "20时23分"
        },
        {
          "title": "白宫提词员利用特朗普演讲内幕获利逾10万美元，CFTC对其展开调查",
          "url": "https://wallstreetcn.com/livenews/3135177",
          "source": "华尔街见闻-快讯",
          "ranks": [
            27
          ],
          "is_new": false,
          "appearance_count": 1,
          "time_info": "01时28分"
        },
        {
          "title": "白宫新闻秘书Leavitt：美国总统特朗普今晚将谈论选举诚信。 媒体应当播放特朗普今夜的讲话。 重申（特朗普）对沃尔玛的赞赏。 特朗普将前往世界杯决赛现场。",
          "url": "https://wallstreetcn.com/livenews/3135209",
          "source": "华尔街见闻-快讯",
          "ranks": [
            27
          ],
          "is_new": false,
          "appearance_count": 1,
          "time_info": "03时26分"
        },
        {
          "title": "特朗普已在为“输掉中期选举”做准备？他的黄金时段讲话暴露了焦虑",
          "url": "https://flash.jin10.com/detail/20260717111924751800",
          "source": "金十数据",
          "ranks": [
            28
          ],
          "is_new": false,
          "appearance_count": 1,
          "time_info": "12时04分"
        },
        {
          "title": "报道：特朗普帖文花钱就能抢先看",
          "url": "https://wallstreetcn.com/livenews/3135311",
          "source": "华尔街见闻-快讯",
          "ranks": [
            28
          ],
          "is_new": false,
          "appearance_count": 1,
          "time_info": "08时19分"
        },
        {
          "title": "欧盟推出银行业改革以回应特朗普的放松监管政策。（彭博）",
          "url": "https://wallstreetcn.com/livenews/3135739",
          "source": "华尔街见闻-快讯",
          "ranks": [
            29
          ],
          "is_new": true,
          "appearance_count": 1,
          "time_info": "22时32分"
        }
      ]
    },
    {
      "keyword_group": "谷歌 google gemini",
      "match_count": 17,
      "titles": [
        {
          "title": "巴菲特罕见发声：当每个人都喜欢赌博时，很难找到价值，谷歌能击败95%华尔街推的票",
          "url": "https://wallstreetcn.com/articles/3777063",
          "source": "华尔街见闻",
          "ranks": [
            2
          ],
          "is_new": false,
          "appearance_count": 9,
          "time_info": "[00时27分 ~ 06时19分]"
        },
        {
          "title": "谷歌Gemini模型发布延期传闻引发担忧 股价盘中跳水逾3%",
          "url": "https://www.cls.cn/detail/2428944",
          "source": "财联社热门",
          "ranks": [
            9,
            7,
            5,
            6
          ],
          "is_new": false,
          "appearance_count": 8,
          "time_info": "[08时19分 ~ 14时44分]"
        },
        {
          "title": "谷歌(GOOG.O)在美国上线搜索AI模式应用集成功能，支持与更多应用协同。",
          "url": "https://flash.jin10.com/detail/20260717001129809800",
          "source": "金十数据",
          "ranks": [
            1
          ],
          "is_new": false,
          "appearance_count": 1,
          "time_info": "00时28分"
        },
        {
          "title": "谷歌(GOOG.O)：Google Vids上线Gemini Omni和个人数字形象功能，面向Google AI Pro、AI Ultra订阅用户及Workspace企业客户开放。",
          "url": "https://flash.jin10.com/detail/20260717001020905800",
          "source": "金十数据",
          "ranks": [
            3
          ],
          "is_new": false,
          "appearance_count": 1,
          "time_info": "00时28分"
        },
        {
          "title": "谷歌(GOOG.O)推出Gemini Omni，并更新Google Vids个人数字形象功能。",
          "url": "https://flash.jin10.com/detail/20260717000925338800",
          "source": "金十数据",
          "ranks": [
            4
          ],
          "is_new": false,
          "appearance_count": 1,
          "time_info": "00时28分"
        },
        {
          "title": "谷歌盘中跌超4%，有报道称Gemini 3.5 Pro延迟发布",
          "url": "https://flash.jin10.com/detail/20260717032122881800",
          "source": "金十数据",
          "ranks": [
            1,
            7
          ],
          "is_new": false,
          "appearance_count": 2,
          "time_info": "[03时26分 ~ 04时17分]"
        },
        {
          "title": "纳斯达克100指数跌幅扩大至2%，成分股Nebius集团跌14.2%，闪迪跌12.8%，Rocket Labs跌12.2%，希捷科技跌10.6%，西部数据跌10.2%，Astera Labs跌9.8%，迈威尔科技/美满电子、Lumentum、泰瑞达、英特尔至少跌6.9%，谷歌A跌4.7%。 半导体指数跌5%，存储芯片指数维持大约9%的跌幅。 北美科技软件股指数ETF跌幅重新扩大至0.4%，美股盘初一度跌1.9%。",
          "url": "https://wallstreetcn.com/livenews/3135254",
          "source": "华尔街见闻-快讯",
          "ranks": [
            4,
            22
          ],
          "is_new": false,
          "appearance_count": 2,
          "time_info": "[04时17分 ~ 05时20分]"
        },
        {
          "title": "欧盟要求谷歌开放安卓AI功能并共享搜索数据",
          "url": "https://wallstreetcn.com/livenews/3135211",
          "source": "华尔街见闻-快讯",
          "ranks": [
            8,
            25
          ],
          "is_new": false,
          "appearance_count": 2,
          "time_info": "[02时21分 ~ 03时26分]"
        },
        {
          "title": "谷歌A跌幅扩大至2.7%。",
          "url": "https://wallstreetcn.com/livenews/3135230",
          "source": "华尔街见闻-快讯",
          "ranks": [
            8,
            25
          ],
          "is_new": false,
          "appearance_count": 2,
          "time_info": "[03时26分 ~ 04时17分]"
        },
        {
          "title": "谷歌母公司Alphabet（谷歌A）重挫5%刷新日低，报道称谷歌Gemini模型将推迟发布。",
          "url": "https://wallstreetcn.com/livenews/3135246",
          "source": "华尔街见闻-快讯",
          "ranks": [
            10,
            28
          ],
          "is_new": false,
          "appearance_count": 2,
          "time_info": "[04时17分 ~ 05时20分]"
        },
        {
          "title": "谷歌(GOOG.O)日内跌近3%，有消息称谷歌Gemini 3.5 Pro推迟发布。",
          "url": "https://flash.jin10.com/detail/20260717022948795800",
          "source": "金十数据",
          "ranks": [
            19,
            25
          ],
          "is_new": false,
          "appearance_count": 2,
          "time_info": "[03时26分 ~ 04时17分]"
        },
        {
          "title": "市场消息：英特尔(INTC.O)正在探索基于谷歌云(GOOG.O)的解决方案，以帮助团队简化市场营销和沟通工作流程。",
          "url": "https://flash.jin10.com/detail/20260717000606202800",
          "source": "金十数据",
          "ranks": [
            6
          ],
          "is_new": false,
          "appearance_count": 1,
          "time_info": "00时28分"
        },
        {
          "title": "市场消息：英特尔(INTC.O)将整合先进的Gemini驱动的生成式人工智能，覆盖其全球员工。",
          "url": "https://flash.jin10.com/detail/20260717000518313800",
          "source": "金十数据",
          "ranks": [
            8
          ],
          "is_new": false,
          "appearance_count": 1,
          "time_info": "00时28分"
        },
        {
          "title": "市场消息：英特尔(INTC.O)与谷歌云(GOOG.O)合作推动英特尔企业人工智能转型。",
          "url": "https://flash.jin10.com/detail/20260717000450810800",
          "source": "金十数据",
          "ranks": [
            9
          ],
          "is_new": false,
          "appearance_count": 1,
          "time_info": "00时28分"
        },
        {
          "title": "报道：谷歌Gemini旗舰模型发布推迟，技术能力未达预期目标",
          "url": "https://wallstreetcn.com/livenews/3135223",
          "source": "华尔街见闻-快讯",
          "ranks": [
            14
          ],
          "is_new": false,
          "appearance_count": 1,
          "time_info": "03时26分"
        },
        {
          "title": "谷歌A收跌4.4%，市值蒸发2000亿美元。 标普500指数的11个板块中，日用品板块收涨2.9%，保健、房地产板块至少涨2.1%，能源板块涨1%，信息技术/可选消费板块跌1.77%，电信板块跌2.85%。 在标普500指数的所有成分股里，谷歌A跌幅靠前，在标普电信板块，谷歌A跌幅仅次于回声星通信（ECHO）——后者收跌5.21%。",
          "url": "https://wallstreetcn.com/livenews/3135262",
          "source": "华尔街见闻-快讯",
          "ranks": [
            16
          ],
          "is_new": false,
          "appearance_count": 1,
          "time_info": "05时20分"
        },
        {
          "title": "谷歌Gemini 3.5 Pro交付进度落后计划数月，因技术能力未达预期目标",
          "url": "https://flash.jin10.com/detail/20260717021710042800",
          "source": "金十数据",
          "ranks": [
            24
          ],
          "is_new": false,
          "appearance_count": 1,
          "time_info": "03时26分"
        }
      ]
    },
    {
      "keyword_group": "美债 国债",
      "match_count": 14,
      "titles": [
        {
          "title": "美国至7月10日当周外国央行持有美国国债 6.39亿美元，前值-286.05亿美元。",
          "url": "https://flash.jin10.com/detail/20260717043052458800",
          "source": "金十数据",
          "ranks": [
            7,
            24
          ],
          "is_new": false,
          "appearance_count": 2,
          "time_info": "[05时20分 ~ 06时19分]"
        },
        {
          "title": "德国两年期国债收益率涨超2个基点",
          "url": "https://wallstreetcn.com/livenews/3135198",
          "source": "华尔街见闻-快讯",
          "ranks": [
            7,
            20
          ],
          "is_new": false,
          "appearance_count": 2,
          "time_info": "[01时28分 ~ 02时21分]"
        },
        {
          "title": "美债收益率普遍涨超1个基点",
          "url": "https://wallstreetcn.com/livenews/3135247",
          "source": "华尔街见闻-快讯",
          "ranks": [
            9,
            27
          ],
          "is_new": false,
          "appearance_count": 2,
          "time_info": "[04时17分 ~ 05时20分]"
        },
        {
          "title": "日本30年期国债收益率上升6个基点至3.89%。 日本40年期国债收益率上升5.5个基点至3.88%。",
          "url": "https://wallstreetcn.com/livenews/3135512",
          "source": "华尔街见闻-快讯",
          "ranks": [
            9,
            25
          ],
          "is_new": false,
          "appearance_count": 2,
          "time_info": "[14时44分 ~ 15时38分]"
        },
        {
          "title": "美国财政部拍卖四周期国债，得标利率3.660，投标倍数2.57。 拍卖八周期国债，得标利率3.650%，投标倍数2.84。",
          "url": "https://wallstreetcn.com/livenews/3135174",
          "source": "华尔街见闻-快讯",
          "ranks": [
            13,
            29
          ],
          "is_new": false,
          "appearance_count": 2,
          "time_info": "[00时28分 ~ 01时28分]"
        },
        {
          "title": "瑞银资产管理高管看空美债 认为德债是极佳的防御性配置选择",
          "url": "https://wallstreetcn.com/livenews/3135669",
          "source": "华尔街见闻-快讯",
          "ranks": [
            13,
            27
          ],
          "is_new": false,
          "appearance_count": 2,
          "time_info": "[19时28分 ~ 20时23分]"
        },
        {
          "title": "国债期货早盘收盘，30年期主力合约涨0.19%，10年期主力合约涨0.05%，5年期主力合约涨0.05%，2年期主力合约涨0.02%。",
          "url": "https://wallstreetcn.com/livenews/3135446",
          "source": "华尔街见闻-快讯",
          "ranks": [
            7
          ],
          "is_new": false,
          "appearance_count": 1,
          "time_info": "12时04分"
        },
        {
          "title": "逾30年的美债多头Hoisington因通胀和债务加剧转而看空",
          "url": "https://wallstreetcn.com/livenews/3135325",
          "source": "华尔街见闻-快讯",
          "ranks": [
            14
          ],
          "is_new": false,
          "appearance_count": 1,
          "time_info": "08时19分"
        },
        {
          "title": "国债期货午盘收盘",
          "url": "https://flash.jin10.com/detail/20260717151904161800",
          "source": "金十数据",
          "ranks": [
            15
          ],
          "is_new": false,
          "appearance_count": 1,
          "time_info": "15时38分"
        },
        {
          "title": "国债期货早盘收盘",
          "url": "https://flash.jin10.com/detail/20260717113140230800",
          "source": "金十数据",
          "ranks": [
            16
          ],
          "is_new": false,
          "appearance_count": 1,
          "time_info": "12时04分"
        },
        {
          "title": "国债期货收盘，30年期主力合约涨0.24%，10年期主力合约涨0.04%，5年期主力合约涨0.02%，2年期主力合约涨0.01%。",
          "url": "https://wallstreetcn.com/livenews/3135552",
          "source": "华尔街见闻-快讯",
          "ranks": [
            21
          ],
          "is_new": false,
          "appearance_count": 1,
          "time_info": "16时41分"
        },
        {
          "title": "美国至7月16日8周国债竞拍-得标利率 3.65%，前值3.635%。",
          "url": "https://flash.jin10.com/detail/20260716233243684800",
          "source": "金十数据",
          "ranks": [
            23
          ],
          "is_new": false,
          "appearance_count": 1,
          "time_info": "00时28分"
        },
        {
          "title": "美国至7月16日8周国债竞拍-投标倍数 2.84，前值2.95。",
          "url": "https://flash.jin10.com/detail/20260716233240252800",
          "source": "金十数据",
          "ranks": [
            24
          ],
          "is_new": false,
          "appearance_count": 1,
          "time_info": "00时28分"
        },
        {
          "title": "美国至7月16日8周国债竞拍-得标利率配置百分比 46.6%，前值68.8%。",
          "url": "https://flash.jin10.com/detail/20260716233219919800",
          "source": "金十数据",
          "ranks": [
            25
          ],
          "is_new": false,
          "appearance_count": 1,
          "time_info": "00时28分"
        }
      ]
    },
    {
      "keyword_group": "原油",
      "match_count": 13,
      "titles": [
        {
          "title": "WTI原油向上触及80美元/桶，日内涨0.69%。",
          "url": "https://flash.jin10.com/detail/20260717170150528800",
          "source": "金十数据",
          "ranks": [
            2
          ],
          "is_new": false,
          "appearance_count": 1,
          "time_info": "17时33分"
        },
        {
          "title": "布伦特原油站上85美元/桶，日内涨1.06%。",
          "url": "https://flash.jin10.com/detail/20260717191607970800",
          "source": "金十数据",
          "ranks": [
            2
          ],
          "is_new": false,
          "appearance_count": 1,
          "time_info": "19时28分"
        },
        {
          "title": "布伦特原油日内涨幅达3.0%，报86.79美元/桶；WTI原油日内涨幅达3.0%，报80.67美元/桶。",
          "url": "https://wallstreetcn.com/livenews/3135734",
          "source": "华尔街见闻-快讯",
          "ranks": [
            2
          ],
          "is_new": false,
          "appearance_count": 1,
          "time_info": "21时32分"
        },
        {
          "title": "中东烽火重燃原油反弹，国内油价今晚上调",
          "url": "https://m.thepaper.cn/newsDetail_forward_33605034",
          "source": "澎湃新闻",
          "ranks": [
            19,
            17,
            13
          ],
          "is_new": false,
          "appearance_count": 5,
          "time_info": "[18时32分 ~ 21时31分]"
        },
        {
          "title": "WTI 8月原油期货收跌0.65美元，跌幅0.82%，报78.95美元/桶。 布伦特9月原油期货收跌0.72美元，跌幅0.85%，报84.23美元/桶。 中东Abu Dhabi Murban原油期货涨0.75%，报79.14美元/桶。 NYMEX 8月天然气期货收报2.8580美元/百万英热单位。 NYMEX 8月汽油期货收报3.2847美元/加仑，NYMEX 8月取暖油期货收报4.0307美元/加仑。",
          "url": "https://wallstreetcn.com/livenews/3135233",
          "source": "华尔街见闻-快讯",
          "ranks": [
            5,
            22
          ],
          "is_new": false,
          "appearance_count": 2,
          "time_info": "[03时26分 ~ 04时17分]"
        },
        {
          "title": "上期所原油期货2609合约夜盘收跌0.46%，报514.40元人民币/桶。 沪金夜盘收跌1.34%，沪银收跌3.15%。",
          "url": "https://wallstreetcn.com/livenews/3135232",
          "source": "华尔街见闻-快讯",
          "ranks": [
            6,
            23
          ],
          "is_new": false,
          "appearance_count": 2,
          "time_info": "[03时26分 ~ 04时17分]"
        },
        {
          "title": "布伦特原油日内涨幅达2.0%，报85.95美元/桶。WTI原油涨超2%，报79.85美元/桶。",
          "url": "https://wallstreetcn.com/livenews/3135673",
          "source": "华尔街见闻-快讯",
          "ranks": [
            9,
            23
          ],
          "is_new": false,
          "appearance_count": 2,
          "time_info": "[19时28分 ~ 20时23分]"
        },
        {
          "title": "布伦特原油期货结算价为每桶84.23美元，下跌72美分，跌幅0.85%。",
          "url": "https://flash.jin10.com/detail/20260717025024712800",
          "source": "金十数据",
          "ranks": [
            11,
            17
          ],
          "is_new": false,
          "appearance_count": 2,
          "time_info": "[03时26分 ~ 04时17分]"
        },
        {
          "title": "WTI原油日内跌幅达1.0%，报78.31美元/桶。",
          "url": "https://wallstreetcn.com/livenews/3135207",
          "source": "华尔街见闻-快讯",
          "ranks": [
            12,
            29
          ],
          "is_new": false,
          "appearance_count": 2,
          "time_info": "[02时21分 ~ 03时26分]"
        },
        {
          "title": "美国原油期货结算价为每桶78.95美元，下跌65美分，跌幅0.82%。",
          "url": "https://flash.jin10.com/detail/20260717023132634800",
          "source": "金十数据",
          "ranks": [
            16,
            22
          ],
          "is_new": false,
          "appearance_count": 2,
          "time_info": "[03时26分 ~ 04时17分]"
        },
        {
          "title": "布伦特原油日内涨超1.00%，现报84.96美元/桶。",
          "url": "https://flash.jin10.com/detail/20260717191131468800",
          "source": "金十数据",
          "ranks": [
            9
          ],
          "is_new": false,
          "appearance_count": 1,
          "time_info": "19时28分"
        },
        {
          "title": "WTI原油日内跌幅达2.00%，现报78.13美元/桶。",
          "url": "https://flash.jin10.com/detail/20260717014238553800",
          "source": "金十数据",
          "ranks": [
            14
          ],
          "is_new": false,
          "appearance_count": 1,
          "time_info": "02时21分"
        },
        {
          "title": "WTI原油期货向上触及81美元/桶，日内涨1.78%。WTI原油日内走高2美元，现报81.47美元/桶，涨幅2.53%。",
          "url": "https://flash.jin10.com/detail/20260717210846697800",
          "source": "金十数据",
          "ranks": [
            20
          ],
          "is_new": false,
          "appearance_count": 1,
          "time_info": "21时32分"
        }
      ]
    },
    {
      "keyword_group": "chatgpt openai",
      "match_count": 6,
      "titles": [
        {
          "title": "“雷曼时刻”在逼近？大空头1.5万字长文起底：OpenAI必将崩溃，全球股市恐遭清算",
          "url": "https://wallstreetcn.com/articles/3777152",
          "source": "华尔街见闻",
          "ranks": [
            10,
            8,
            7,
            6,
            5
          ],
          "is_new": false,
          "appearance_count": 17,
          "time_info": "[11时01分 ~ 22时32分]"
        },
        {
          "title": "何为AI泡沫？分析师：OpenAI就是“业界雷曼兄弟”，一倒全市场将崩盘！",
          "url": "https://www.cls.cn/detail/2429226",
          "source": "财联社热门",
          "ranks": [
            13
          ],
          "is_new": false,
          "appearance_count": 2,
          "time_info": "[17时33分 ~ 18时32分]"
        },
        {
          "title": "一些现就职于OpenAI的前苹果员工收到了法律信函。（英国《金融时报》）",
          "url": "https://wallstreetcn.com/livenews/3135650",
          "source": "华尔街见闻-快讯",
          "ranks": [
            13,
            27
          ],
          "is_new": false,
          "appearance_count": 2,
          "time_info": "[18时32分 ~ 19时28分]"
        },
        {
          "title": "银河通用创始人王鹤：具身智能的ChatGPT时刻2028年有望到来",
          "url": "https://wallstreetcn.com/livenews/3135571",
          "source": "华尔街见闻-快讯",
          "ranks": [
            6
          ],
          "is_new": false,
          "appearance_count": 1,
          "time_info": "16时41分"
        },
        {
          "title": "OpenAI董事长称对其他公司的商业机密“没有兴趣”",
          "url": "https://flash.jin10.com/detail/20260717022344954800",
          "source": "金十数据",
          "ranks": [
            22
          ],
          "is_new": false,
          "appearance_count": 1,
          "time_info": "03时26分"
        },
        {
          "title": "OpenAI董事长：IPO时间暂无最新消息",
          "url": "https://flash.jin10.com/detail/20260717004805940800",
          "source": "金十数据",
          "ranks": [
            24
          ],
          "is_new": false,
          "appearance_count": 1,
          "time_info": "01时28分"
        }
      ]
    },
    {
      "keyword_group": "金价 银价",
      "match_count": 6,
      "titles": [
        {
          "title": "【早报】美股存储股再遭重挫；美军连续空袭伊朗；油价、金价双双下跌；多只芯片股发布重要公告",
          "url": "https://www.cls.cn/detail/2428987",
          "source": "财联社热门",
          "ranks": [
            3,
            1
          ],
          "is_new": false,
          "appearance_count": 10,
          "time_info": "[08时19分 ~ 15时38分]"
        },
        {
          "title": "伯恩斯坦：将2026年黄金价格目标上调至4533美元/盎司，因各国央行正在实现储备多元化，且预计美联储在未来一年内最多只会加息一两次。",
          "url": "https://flash.jin10.com/detail/20260717075253072800",
          "source": "金十数据",
          "ranks": [
            1
          ],
          "is_new": false,
          "appearance_count": 1,
          "time_info": "08时19分"
        },
        {
          "title": "金银价格重挫背后",
          "url": "https://www.toutiao.com/trending/7663411646760488491/",
          "source": "今日头条",
          "ranks": [
            27
          ],
          "is_new": false,
          "appearance_count": 2,
          "time_info": "[19时27分 ~ 19时28分]"
        },
        {
          "title": "【世界黄金协会：中国市场黄金ETF上半年实现显著流入】7月17日，世界黄金协会数据显示，6月金价走弱，抹去前期涨幅，上半年最终以下跌收官。尽管6月有流出，中国市场黄金ETF上半年仍实现显著流入，推动资产管理总规模（AUM）小幅升至2430亿元人民币，总持仓增加29吨至277吨。6月，中国市场黄金ETF流出150亿元人民币，为有记录以来最疲弱的单月表现。",
          "url": "https://wallstreetcn.com/livenews/3135688",
          "source": "华尔街见闻-快讯",
          "ranks": [
            13
          ],
          "is_new": false,
          "appearance_count": 1,
          "time_info": "20时23分"
        },
        {
          "title": "金价跌破4000美元关口 分析师：市场更重视美国利率更高更久的风险",
          "url": "https://flash.jin10.com/detail/20260717160655635800",
          "source": "金十数据",
          "ranks": [
            26
          ],
          "is_new": false,
          "appearance_count": 1,
          "time_info": "16时41分"
        },
        {
          "title": "金十图示：2026年07月17日（周五）上海金早盘价为868.89元/克，较国际金价（约为867.68元/克），高1.21元/克。",
          "url": "https://flash.jin10.com/detail/20260717101800598800",
          "source": "金十数据",
          "ranks": [
            27
          ],
          "is_new": false,
          "appearance_count": 1,
          "time_info": "11时02分"
        }
      ]
    },
    {
      "keyword_group": "美元",
      "match_count": 3,
      "titles": [
        {
          "title": "美元指数16日上涨",
          "url": "https://flash.jin10.com/detail/20260717045050743800",
          "source": "金十数据",
          "ranks": [
            3,
            20
          ],
          "is_new": false,
          "appearance_count": 2,
          "time_info": "[05时20分 ~ 06时19分]"
        },
        {
          "title": "最近24小时，MarketVectorTM数字资产100小盘指数跌0.40%，暂报2197.47点，北京时间16:16曾刷新日低至2165.11点。 MarketVectorTM数字资产100中盘指数跌0.97%，报2578.78点。 MarketVector数字资产100指数跌1.16%，报12825.74点，16:00前后曾显著扩大跌幅。 目前，Solana跌1.30%，狗狗币跌0.60%，XRP持平。 比特币跌0.71%，暂报64418.58美元；以太坊跌2.49%，暂报1875.89美元。",
          "url": "https://wallstreetcn.com/livenews/3135199",
          "source": "华尔街见闻-快讯",
          "ranks": [
            6,
            19
          ],
          "is_new": false,
          "appearance_count": 2,
          "time_info": "[01时28分 ~ 02时21分]"
        },
        {
          "title": "美元指数涨约0.3%",
          "url": "https://wallstreetcn.com/livenews/3135248",
          "source": "华尔街见闻-快讯",
          "ranks": [
            8,
            26
          ],
          "is_new": false,
          "appearance_count": 2,
          "time_info": "[04时17分 ~ 05时20分]"
        }
      ]
    },
    {
      "keyword_group": "DeepSeek 梁文锋",
      "match_count": 2,
      "titles": [
        {
          "title": "梁文锋重仓打新，万亿长鑫被抢疯了",
          "url": "https://wallstreetcn.com/articles/3777116",
          "source": "华尔街见闻",
          "ranks": [
            8,
            7,
            4,
            5,
            6
          ],
          "is_new": false,
          "appearance_count": 25,
          "time_info": "[00时27分 ~ 19时28分]"
        },
        {
          "title": "梁文锋打新长鑫科技",
          "url": "https://www.toutiao.com/trending/7663049647610400299/",
          "source": "今日头条",
          "ranks": [
            14,
            12,
            13,
            16
          ],
          "is_new": false,
          "appearance_count": 10,
          "time_info": "[00时27分 ~ 08时19分]"
        }
      ]
    }
  ],
  "report_image_url": "https://joyce677.github.io/TrendRadar/img/news.jpg"
}