{
  "generated_at": "2026-04-09T18:23:06.813491+08:00",
  "total_titles_processed": 1828,
  "failed_sources": [],
  "trends": [
    {
      "keyword_group": "特朗普",
      "match_count": 103,
      "titles": [
        {
          "title": "特朗普威胁对向伊朗供武国家加税",
          "url": "https://news.ifeng.com/c/8sA9vYHDTBG",
          "source": "凤凰网",
          "ranks": [
            2,
            3
          ],
          "is_new": false,
          "appearance_count": 13,
          "time_info": "[00时23分 ~ 10时59分]"
        },
        {
          "title": "万斯威胁：特朗普没有多少耐心，希望尽快取得进展",
          "url": "https://news.ifeng.com/c/8sAEfxVEMqZ",
          "source": "凤凰网",
          "ranks": [
            5,
            3
          ],
          "is_new": false,
          "appearance_count": 16,
          "time_info": "[00时23分 ~ 12时54分]"
        },
        {
          "title": "特朗普提议与伊朗联合管理霍尔木兹海峡",
          "url": "https://news.ifeng.com/c/8sADQbyVMoK",
          "source": "凤凰网",
          "ranks": [
            4
          ],
          "is_new": false,
          "appearance_count": 13,
          "time_info": "[00时23分 ~ 10时59分]"
        },
        {
          "title": "“北约盟友没帮忙，特朗普打算这样惩罚”",
          "url": "https://news.ifeng.com/c/8sB098ZojvN",
          "source": "凤凰网",
          "ranks": [
            4,
            3
          ],
          "is_new": false,
          "appearance_count": 9,
          "time_info": "[11时59分 ~ 16时27分]"
        },
        {
          "title": "特朗普说美媒披露的10项停战条款是“假新闻”",
          "url": "https://news.ifeng.com/c/8sBBnRWw3el",
          "source": "凤凰网",
          "ranks": [
            5,
            4,
            2
          ],
          "is_new": false,
          "appearance_count": 9,
          "time_info": "[11时59分 ~ 16时27分]"
        },
        {
          "title": "以色列袭击黎巴嫩后霍尔木兹海峡再关闭，伊朗据称将收“过路费”且限量放行，白宫称特朗普反对收费",
          "url": "https://wallstreetcn.com/articles/3769517",
          "source": "华尔街见闻",
          "ranks": [
            10,
            2,
            1
          ],
          "is_new": false,
          "appearance_count": 18,
          "time_info": "[08时07分 ~ 18时23分]"
        },
        {
          "title": "威胁“摧毁文明”不到12小时，特朗普接受停火两周提议，伊朗称伊美谈判10日开始",
          "url": "https://wallstreetcn.com/articles/3769436",
          "source": "华尔街见闻",
          "ranks": [
            1
          ],
          "is_new": false,
          "appearance_count": 8,
          "time_info": "[00时23分 ~ 07时12分]"
        },
        {
          "title": "距离“最后期限”不到一个半小时，特朗普同意与伊朗停火两周",
          "url": "https://m.thepaper.cn/newsDetail_forward_32921095",
          "source": "澎湃新闻",
          "ranks": [
            1
          ],
          "is_new": false,
          "appearance_count": 8,
          "time_info": "[00时23分 ~ 07时12分]"
        },
        {
          "title": "美副总统万斯：美伊停火为“脆弱休战” 特朗普“急于看到进展”",
          "url": "https://www.cls.cn/detail/2338136",
          "source": "财联社热门",
          "ranks": [
            1,
            2
          ],
          "is_new": false,
          "appearance_count": 8,
          "time_info": "[00时23分 ~ 07时12分]"
        },
        {
          "title": "停火首日即遇变数：特朗普“反复横跳”，不承认伊朗“10点计划”做基础",
          "url": "https://wallstreetcn.com/articles/3769534",
          "source": "华尔街见闻",
          "ranks": [
            10,
            8,
            5,
            4,
            3
          ],
          "is_new": false,
          "appearance_count": 15,
          "time_info": "[10时58分 ~ 18时23分]"
        },
        {
          "title": "特朗普：美媒披露的伊方10项停火条款是“假新闻”",
          "url": "https://www.cls.cn/detail/2338839",
          "source": "财联社热门",
          "ranks": [
            10,
            8,
            6,
            5,
            2,
            1
          ],
          "is_new": false,
          "appearance_count": 11,
          "time_info": "[12时54分 ~ 18时23分]"
        },
        {
          "title": "特朗普最后一刻TACO：中间人来回传话，一天内多轮修改方案，伊朗高层最终拍板，幕后一片混乱",
          "url": "https://wallstreetcn.com/articles/3769471",
          "source": "华尔街见闻",
          "ranks": [
            9,
            8,
            5,
            6
          ],
          "is_new": false,
          "appearance_count": 21,
          "time_info": "[00时23分 ~ 15时29分]"
        },
        {
          "title": "特朗普：所有美国舰船、飞机和军事人员将继续留在伊朗周围",
          "url": "https://news.ifeng.com/c/8sBFKpB7gj3",
          "source": "凤凰网",
          "ranks": [
            6,
            4
          ],
          "is_new": false,
          "appearance_count": 8,
          "time_info": "[13时33分 ~ 17时25分]"
        },
        {
          "title": "美伊停火的关键斡旋者：与特朗普私交甚好的巴基斯坦陆军元帅",
          "url": "https://news.ifeng.com/c/8sA49KKqTTa",
          "source": "凤凰网",
          "ranks": [
            7,
            8
          ],
          "is_new": false,
          "appearance_count": 13,
          "time_info": "[00时23分 ~ 10时59分]"
        },
        {
          "title": "特朗普：若谈判不顺，美国能轻易恢复对伊军事行动，万斯：\"脆弱休战\"基础初步形成",
          "url": "https://wallstreetcn.com/articles/3769486",
          "source": "华尔街见闻",
          "ranks": [
            9,
            8,
            6
          ],
          "is_new": false,
          "appearance_count": 18,
          "time_info": "[08时07分 ~ 18时23分]"
        },
        {
          "title": "深度特写：特朗普是如何把美国\"拖入\"伊朗战争的？",
          "url": "https://wallstreetcn.com/articles/3769466",
          "source": "华尔街见闻",
          "ranks": [
            10,
            7,
            8,
            6
          ],
          "is_new": false,
          "appearance_count": 16,
          "time_info": "[06时11分 ~ 16时27分]"
        },
        {
          "title": "特朗普：提议美伊联管霍尔木兹海峡，威胁向伊朗供武国家征收50%关税",
          "url": "https://wallstreetcn.com/articles/3769503",
          "source": "华尔街见闻",
          "ranks": [
            10,
            9,
            7,
            8
          ],
          "is_new": false,
          "appearance_count": 12,
          "time_info": "[09时31分 ~ 18时23分]"
        },
        {
          "title": "吹嘘伊朗乞求停火，美防长被打脸：是特朗普先退了",
          "url": "https://news.ifeng.com/c/8sALx5qaI3W",
          "source": "凤凰网",
          "ranks": [
            9
          ],
          "is_new": false,
          "appearance_count": 11,
          "time_info": "[09时31分 ~ 15时29分]"
        },
        {
          "title": "外交部回应特朗普：关税战没有赢家！",
          "url": "https://www.baidu.com/s?wd=%E5%A4%96%E4%BA%A4%E9%83%A8%E5%9B%9E%E5%BA%94%E7%89%B9%E6%9C%97%E6%99%AE%EF%BC%9A%E5%85%B3%E7%A8%8E%E6%88%98%E6%B2%A1%E6%9C%89%E8%B5%A2%E5%AE%B6%EF%BC%81",
          "source": "百度热搜",
          "ranks": [
            1,
            2
          ],
          "is_new": false,
          "appearance_count": 5,
          "time_info": "[16时27分 ~ 18时23分]"
        },
        {
          "title": "尴尬！万斯演讲现场给特朗普打电话，手机那头传来：对不起…",
          "url": "https://v.ifeng.com/c/8s9rZeXMBcT",
          "source": "凤凰网",
          "ranks": [
            10
          ],
          "is_new": false,
          "appearance_count": 13,
          "time_info": "[00时23分 ~ 10时59分]"
        },
        {
          "title": "特朗普宣布对伊朗武器供应国加征 50% 关税，如何看待这一表态？可能带来哪些影响？",
          "url": "https://www.zhihu.com/question/2025299647992709378",
          "source": "知乎",
          "ranks": [
            11,
            20
          ],
          "is_new": false,
          "appearance_count": 13,
          "time_info": "[00时23分 ~ 13时34分]"
        },
        {
          "title": "外交部回应特朗普认为是中国促使伊朗同意停火，「中方一直积极致力于促和止战」，哪些信息值得关注？",
          "url": "https://www.zhihu.com/question/2025238372327723742",
          "source": "知乎",
          "ranks": [
            11,
            14,
            20
          ],
          "is_new": false,
          "appearance_count": 13,
          "time_info": "[10时58分 ~ 17时25分]"
        },
        {
          "title": "美媒披露特朗普发动伊朗战争内幕：“全凭直觉”，除万斯外无人反对",
          "url": "https://m.thepaper.cn/newsDetail_forward_32927020",
          "source": "澎湃新闻",
          "ranks": [
            20,
            14,
            15,
            13,
            12
          ],
          "is_new": false,
          "appearance_count": 16,
          "time_info": "[09时31分 ~ 18时23分]"
        },
        {
          "title": "脆弱的停火：以色列依旧“搅屎棍”，特朗普还是“来回变”",
          "url": "https://wallstreetcn.com/articles/3769537",
          "source": "华尔街见闻",
          "ranks": [
            10,
            8,
            7,
            4
          ],
          "is_new": false,
          "appearance_count": 8,
          "time_info": "[14时27分 ~ 18时23分]"
        },
        {
          "title": "伊朗终止同美直接外交联系、仍通过调解人沟通，巴基斯坦提议宽限两周、特朗普将回应，报道称很快有好消息",
          "url": "https://wallstreetcn.com/articles/3769420",
          "source": "华尔街见闻",
          "ranks": [
            7
          ],
          "is_new": false,
          "appearance_count": 6,
          "time_info": "[00时23分 ~ 05时13分]"
        },
        {
          "title": "据美国财经媒体Semafor：特朗普政府可能很快放松对伊朗石油的制裁，以帮助稳定全球石油供应，并防止燃料价格进一步上涨。",
          "url": "https://flash.jin10.com/detail/20260409175230039800",
          "source": "金十数据",
          "ranks": [
            1
          ],
          "is_new": true,
          "appearance_count": 1,
          "time_info": "18时23分"
        },
        {
          "title": "特朗普：所有美国舰船、飞机和军事人员将继续留在伊朗周围",
          "url": "https://wallstreetcn.com/livenews/3084761",
          "source": "华尔街见闻-快讯",
          "ranks": [
            1
          ],
          "is_new": false,
          "appearance_count": 1,
          "time_info": "12时00分"
        },
        {
          "title": "特朗普：美媒披露的伊方10项停火条款是“假新闻”",
          "url": "https://m.thepaper.cn/newsDetail_forward_32932623",
          "source": "澎湃新闻",
          "ranks": [
            19
          ],
          "is_new": false,
          "appearance_count": 6,
          "time_info": "[15时29分 ~ 18时23分]"
        },
        {
          "title": "以色列总理内塔尼亚胡：我们取得了巨大的成就。特朗普和我是朋友。任何忽视这些成就的人都是错误的。",
          "url": "https://flash.jin10.com/detail/20260409012121522800",
          "source": "金十数据",
          "ranks": [
            2
          ],
          "is_new": false,
          "appearance_count": 1,
          "time_info": "01时22分"
        },
        {
          "title": "北约秘书长吕特：与美国总统特朗普进行了非常坦诚、开放的讨论。",
          "url": "https://flash.jin10.com/detail/20260409063724672800",
          "source": "金十数据",
          "ranks": [
            2
          ],
          "is_new": false,
          "appearance_count": 1,
          "time_info": "07时12分"
        },
        {
          "title": "WTI原油期货维持3%的涨幅，特朗普称美国武器将继续部署在伊朗及周边地区，直到真正协议得到全面遵守",
          "url": "https://wallstreetcn.com/livenews/3084759",
          "source": "华尔街见闻-快讯",
          "ranks": [
            2
          ],
          "is_new": false,
          "appearance_count": 1,
          "time_info": "12时00分"
        },
        {
          "title": "以色列媒体报道，在宣布停火前，以色列总理内塔尼亚胡与特朗普通话时表示反对与伊朗达成协议。",
          "url": "https://flash.jin10.com/detail/20260409063444053800",
          "source": "金十数据",
          "ranks": [
            3
          ],
          "is_new": false,
          "appearance_count": 1,
          "time_info": "07时12分"
        },
        {
          "title": "特朗普：我们的军队正在休整 海峡必须开放",
          "url": "https://flash.jin10.com/detail/20260409114729043800",
          "source": "金十数据",
          "ranks": [
            3
          ],
          "is_new": false,
          "appearance_count": 1,
          "time_info": "12时00分"
        },
        {
          "title": "关税战没有赢家！外交部回应特朗普关税言论",
          "url": "https://wallstreetcn.com/livenews/3084878",
          "source": "华尔街见闻-快讯",
          "ranks": [
            3
          ],
          "is_new": false,
          "appearance_count": 1,
          "time_info": "15时29分"
        },
        {
          "title": "特朗普：美军驻留伊朗，违约就“开火”，规模将前所未有",
          "url": "https://flash.jin10.com/detail/20260409130825168800",
          "source": "金十数据",
          "ranks": [
            4
          ],
          "is_new": false,
          "appearance_count": 1,
          "time_info": "13时34分"
        },
        {
          "title": "从惊魂到TACO--特朗普震惊世界的12小时",
          "url": "https://wallstreetcn.com/articles/3769455",
          "source": "华尔街见闻",
          "ranks": [
            8
          ],
          "is_new": false,
          "appearance_count": 5,
          "time_info": "[08时07分 ~ 10时59分]"
        },
        {
          "title": "见完北约秘书长 特朗普仍“不解气”",
          "url": "https://wallstreetcn.com/livenews/3084821",
          "source": "华尔街见闻-快讯",
          "ranks": [
            5
          ],
          "is_new": false,
          "appearance_count": 1,
          "time_info": "14时28分"
        },
        {
          "title": "以色列议员公开辱骂特朗普",
          "url": "https://s.weibo.com/weibo?q=%23%E4%BB%A5%E8%89%B2%E5%88%97%E8%AE%AE%E5%91%98%E5%85%AC%E5%BC%80%E8%BE%B1%E9%AA%82%E7%89%B9%E6%9C%97%E6%99%AE%23&t=31&band_rank=14&Refer=top",
          "source": "微博",
          "ranks": [
            14,
            8,
            28
          ],
          "is_new": false,
          "appearance_count": 5,
          "time_info": "[11时59分 ~ 13时34分]"
        },
        {
          "title": "特朗普：美军将“继续驻扎在伊朗境内及其周边”",
          "url": "https://www.cls.cn/detail/2338861",
          "source": "财联社热门",
          "ranks": [
            12,
            10,
            9
          ],
          "is_new": false,
          "appearance_count": 5,
          "time_info": "[16时27分 ~ 18时23分]"
        },
        {
          "title": "中方回应特朗普威胁对向伊朗供武国家加税",
          "url": "https://news.ifeng.com/c/8sBUhB6xiS2",
          "source": "凤凰网",
          "ranks": [
            6
          ],
          "is_new": false,
          "appearance_count": 4,
          "time_info": "[17时24分 ~ 18时23分]"
        },
        {
          "title": "白宫：特朗普将与吕特讨论退出北约事宜",
          "url": "https://wallstreetcn.com/livenews/3084526",
          "source": "华尔街见闻-快讯",
          "ranks": [
            1,
            16,
            25
          ],
          "is_new": false,
          "appearance_count": 3,
          "time_info": "[02时21分 ~ 04时10分]"
        },
        {
          "title": "美国法官阻止特朗普政府终止对5000多名埃塞俄比亚人的法律保护的请求。",
          "url": "https://flash.jin10.com/detail/20260409050230973800",
          "source": "金十数据",
          "ranks": [
            2,
            14
          ],
          "is_new": false,
          "appearance_count": 2,
          "time_info": "[05时13分 ~ 06时11分]"
        },
        {
          "title": "美国白宫：特朗普总统发布公告，根据修订后的《平衡预算和紧急赤字控制法》，调整2027财年的自动减支机制。",
          "url": "https://flash.jin10.com/detail/20260409053704280800",
          "source": "金十数据",
          "ranks": [
            3,
            29
          ],
          "is_new": false,
          "appearance_count": 2,
          "time_info": "[06时11分 ~ 07时12分]"
        },
        {
          "title": "法国总统马克龙：已告知伊朗总统佩泽希齐扬和美国总统特朗普，他们接受停火的决定是最佳选择。",
          "url": "https://flash.jin10.com/detail/20260409045505102800",
          "source": "金十数据",
          "ranks": [
            4,
            16
          ],
          "is_new": false,
          "appearance_count": 2,
          "time_info": "[05时13分 ~ 06时11分]"
        },
        {
          "title": "据一位北约消息人士透露，美国总统特朗普与北约秘书长吕特的会晤仍在进行中。吕特已经在白宫逗留90多分钟了。",
          "url": "https://flash.jin10.com/detail/20260409045503926800",
          "source": "金十数据",
          "ranks": [
            5,
            17
          ],
          "is_new": false,
          "appearance_count": 2,
          "time_info": "[05时13分 ~ 06时11分]"
        },
        {
          "title": "美国总统特朗普：我们将与伊朗通过闭门会议讨论停火协议的条款。",
          "url": "https://wallstreetcn.com/livenews/3084477",
          "source": "华尔街见闻-快讯",
          "ranks": [
            5,
            25
          ],
          "is_new": false,
          "appearance_count": 2,
          "time_info": "[00时23分 ~ 01时22分]"
        },
        {
          "title": "白宫：特朗普认为北约未通过“考验”，将与吕特讨论“退群”",
          "url": "https://wallstreetcn.com/livenews/3084549",
          "source": "华尔街见闻-快讯",
          "ranks": [
            5,
            24
          ],
          "is_new": false,
          "appearance_count": 2,
          "time_info": "[04时10分 ~ 05时13分]"
        },
        {
          "title": "北约秘书长吕特：已经告知美国总统特朗普，欧洲大多数国家一直以来都是有帮助的。 与特朗普进行了非常开诚布公的讨论。（CNN）",
          "url": "https://wallstreetcn.com/livenews/3084618",
          "source": "华尔街见闻-快讯",
          "ranks": [
            5,
            24
          ],
          "is_new": false,
          "appearance_count": 2,
          "time_info": "[07时12分 ~ 08时08分]"
        },
        {
          "title": "在特朗普2.0任期内炒股竟有秘诀：标普十大涨幅日九个和TACO有关",
          "url": "https://www.cls.cn/detail/2338928",
          "source": "财联社热门",
          "ranks": [
            11,
            10,
            9
          ],
          "is_new": false,
          "appearance_count": 4,
          "time_info": "[17时24分 ~ 18时23分]"
        },
        {
          "title": "【白宫：美伊首轮会谈将于11日上午在伊斯兰堡举行】美国白宫新闻秘书莱维特8日在记者会上说，美国和伊朗将于当地时间11日上午在巴基斯坦首都伊斯兰堡举行首轮会谈，美方团队将由副总统万斯、总统特朗普的特使威特科夫和女婿库什纳率领。（新华社）",
          "url": "https://wallstreetcn.com/livenews/3084520",
          "source": "华尔街见闻-快讯",
          "ranks": [
            6,
            21,
            30
          ],
          "is_new": false,
          "appearance_count": 3,
          "time_info": "[02时21分 ~ 04时10分]"
        },
        {
          "title": "关税战没有赢家！外交部回应特朗普关税言论",
          "url": "https://www.cls.cn/detail/2339082",
          "source": "财联社热门",
          "ranks": [
            13
          ],
          "is_new": false,
          "appearance_count": 3,
          "time_info": "[17时25分 ~ 18时23分]"
        },
        {
          "title": "市场消息：法国总统马克龙表示希望停火能得到尊重，包括在黎巴嫩。马克龙与伊朗总统佩泽希齐扬和美国总统特朗普进行了交谈。",
          "url": "https://flash.jin10.com/detail/20260409045044768800",
          "source": "金十数据",
          "ranks": [
            8,
            20
          ],
          "is_new": false,
          "appearance_count": 2,
          "time_info": "[05时13分 ~ 06时11分]"
        },
        {
          "title": "白宫新闻秘书Leavitt：围绕霍尔木兹海峡收费成立合资公司是美国总统特朗普的某个建议。 尚未完全接受伊朗收取通行费。 美国不希望霍尔木兹海峡受到任何限制，包括收费。",
          "url": "https://wallstreetcn.com/livenews/3084518",
          "source": "华尔街见闻-快讯",
          "ranks": [
            8,
            23
          ],
          "is_new": false,
          "appearance_count": 2,
          "time_info": "[02时21分 ~ 03时28分]"
        },
        {
          "title": "美国众议院民主党高层暗示，对推动第25修正案罢免美国总统特朗普持开放态度。",
          "url": "https://flash.jin10.com/detail/20260409044928429800",
          "source": "金十数据",
          "ranks": [
            9,
            21
          ],
          "is_new": false,
          "appearance_count": 2,
          "time_info": "[05时13分 ~ 06时11分]"
        },
        {
          "title": "白宫新闻秘书Leavitt：美国总统特朗普对伊朗发出了一个“非常强大的威胁”。",
          "url": "https://wallstreetcn.com/livenews/3084517",
          "source": "华尔街见闻-快讯",
          "ranks": [
            9,
            24
          ],
          "is_new": false,
          "appearance_count": 2,
          "time_info": "[02时21分 ~ 03时28分]"
        },
        {
          "title": "【内塔尼亚胡：临时停火“并非战争的结束”】以色列总理内塔尼亚胡8日晚发表视频讲话称，美国总统特朗普与伊朗达成的临时停火是与以色列协调的结果。这“并非战争的结束”，而是以方所有既定目标实现过程中的一个阶段。（新华社）",
          "url": "https://wallstreetcn.com/livenews/3084533",
          "source": "华尔街见闻-快讯",
          "ranks": [
            9,
            18
          ],
          "is_new": false,
          "appearance_count": 2,
          "time_info": "[03时28分 ~ 04时10分]"
        },
        {
          "title": "美国总统特朗普考虑惩罚特定的北约成员国。 特朗普的打算还处于早期阶段。 白宫在惩罚北约方面有好几个计划。 美国可能会（在北约）关闭至少一个军事基地，可能是在西班牙的、也可能是在德国的。（华尔街日报）",
          "url": "https://wallstreetcn.com/livenews/3084562",
          "source": "华尔街见闻-快讯",
          "ranks": [
            13,
            30
          ],
          "is_new": false,
          "appearance_count": 2,
          "time_info": "[05时13分 ~ 06时11分]"
        },
        {
          "title": "特朗普说美媒披露的10项停战条款是“假新闻”",
          "url": "https://wallstreetcn.com/livenews/3084742",
          "source": "华尔街见闻-快讯",
          "ranks": [
            14,
            28
          ],
          "is_new": false,
          "appearance_count": 2,
          "time_info": "[12时00分 ~ 12时54分]"
        },
        {
          "title": "WTI原油期货维持3%的涨幅，特朗普：美军将“继续驻扎在伊朗境内及其周边”，直到达成的协议得到全面遵守",
          "url": "https://wallstreetcn.com/livenews/3084759",
          "source": "华尔街见闻-快讯",
          "ranks": [
            16,
            25
          ],
          "is_new": false,
          "appearance_count": 2,
          "time_info": "[12时54分 ~ 13时34分]"
        },
        {
          "title": "特朗普对北约表达不满",
          "url": "https://www.douyin.com/hot/2460339",
          "source": "抖音",
          "ranks": [
            28
          ],
          "is_new": false,
          "appearance_count": 2,
          "time_info": "[18时22分 ~ 18时23分]"
        },
        {
          "title": "特朗普称对向伊朗供武国家征收50%关税，中方回应",
          "url": "https://news.ifeng.com/c/8sBUhB6xiS2",
          "source": "凤凰网",
          "ranks": [
            6
          ],
          "is_new": false,
          "appearance_count": 1,
          "time_info": "16时27分"
        },
        {
          "title": "美国副总统万斯：伊朗人必须采取下一步行动，否则美国总统特朗普将有重返战争的选择。",
          "url": "https://flash.jin10.com/detail/20260409033730491800",
          "source": "金十数据",
          "ranks": [
            6
          ],
          "is_new": false,
          "appearance_count": 1,
          "time_info": "04时10分"
        },
        {
          "title": "北约秘书长吕特与特朗普的会晤结束。",
          "url": "https://flash.jin10.com/detail/20260409053003064800",
          "source": "金十数据",
          "ranks": [
            6
          ],
          "is_new": false,
          "appearance_count": 1,
          "time_info": "06时11分"
        },
        {
          "title": "据美国财经媒体Semafor：特朗普政府将继续放松对俄罗斯石油的制裁。",
          "url": "https://flash.jin10.com/detail/20260409174827281800",
          "source": "金十数据",
          "ranks": [
            8
          ],
          "is_new": true,
          "appearance_count": 1,
          "time_info": "18时23分"
        },
        {
          "title": "特朗普连线绕月飞船讲话后冷场1分钟",
          "url": "https://www.toutiao.com/trending/7625901214111727657/",
          "source": "今日头条",
          "ranks": [
            9
          ],
          "is_new": false,
          "appearance_count": 1,
          "time_info": "15时29分"
        },
        {
          "title": "白宫新闻秘书莱维特：北约经受了考验，但他们失败了。美国总统特朗普期待与北约秘书长吕特进行坦诚对话。",
          "url": "https://flash.jin10.com/detail/20260409014819699800",
          "source": "金十数据",
          "ranks": [
            9
          ],
          "is_new": false,
          "appearance_count": 1,
          "time_info": "02时21分"
        },
        {
          "title": "白宫新闻秘书莱维特：特朗普对伊朗发出了非常严重的威胁。",
          "url": "https://flash.jin10.com/detail/20260409014803108800",
          "source": "金十数据",
          "ranks": [
            10
          ],
          "is_new": false,
          "appearance_count": 1,
          "time_info": "02时21分"
        },
        {
          "title": "美媒：明尼阿波利斯联储顾问菲兰有望成为特朗普的首席经济顾问",
          "url": "https://flash.jin10.com/detail/20260409025634698800",
          "source": "金十数据",
          "ranks": [
            11
          ],
          "is_new": false,
          "appearance_count": 1,
          "time_info": "03时28分"
        },
        {
          "title": "史上最尴尬的极限施压：特朗普嗓门越大，华尔街越想买入？",
          "url": "https://flash.jin10.com/detail/20260409174403639800",
          "source": "金十数据",
          "ranks": [
            11
          ],
          "is_new": true,
          "appearance_count": 1,
          "time_info": "18时23分"
        },
        {
          "title": "特朗普认为是中国促使伊朗同意停火",
          "url": "https://s.weibo.com/weibo?q=%23%E7%89%B9%E6%9C%97%E6%99%AE%E8%AE%A4%E4%B8%BA%E6%98%AF%E4%B8%AD%E5%9B%BD%E4%BF%83%E4%BD%BF%E4%BC%8A%E6%9C%97%E5%90%8C%E6%84%8F%E5%81%9C%E7%81%AB%23&t=31&band_rank=11&Refer=top",
          "source": "微博",
          "ranks": [
            11
          ],
          "is_new": false,
          "appearance_count": 1,
          "time_info": "00时23分"
        },
        {
          "title": "白宫新闻秘书莱维特：特朗普曾提出从霍尔木兹海峡征收费用。",
          "url": "https://flash.jin10.com/detail/20260409014613560800",
          "source": "金十数据",
          "ranks": [
            13
          ],
          "is_new": false,
          "appearance_count": 1,
          "time_info": "02时21分"
        },
        {
          "title": "吕特：欧洲大部分地区都支持特朗普打击伊朗“输出混乱”的能力",
          "url": "https://flash.jin10.com/detail/20260409074647226800",
          "source": "金十数据",
          "ranks": [
            13
          ],
          "is_new": false,
          "appearance_count": 1,
          "time_info": "08时08分"
        },
        {
          "title": "特朗普要惩罚“不帮忙打伊朗”的北约盟国：撤军、关基地",
          "url": "https://flash.jin10.com/detail/20260409101419243800",
          "source": "金十数据",
          "ranks": [
            13
          ],
          "is_new": false,
          "appearance_count": 1,
          "time_info": "10时59分"
        },
        {
          "title": "特朗普：美伊将闭门讨论有意义的停火协议",
          "url": "https://flash.jin10.com/detail/20260409001303107800",
          "source": "金十数据",
          "ranks": [
            14
          ],
          "is_new": false,
          "appearance_count": 1,
          "time_info": "00时23分"
        },
        {
          "title": "白宫新闻秘书莱维特：内塔尼亚胡支持特朗普；以色列是关键盟友。",
          "url": "https://flash.jin10.com/detail/20260409014449312800",
          "source": "金十数据",
          "ranks": [
            14
          ],
          "is_new": false,
          "appearance_count": 1,
          "time_info": "02时21分"
        },
        {
          "title": "美国总统特朗普：这些要点是我们同意停火的基础。",
          "url": "https://flash.jin10.com/detail/20260409000735272800",
          "source": "金十数据",
          "ranks": [
            15
          ],
          "is_new": false,
          "appearance_count": 1,
          "time_info": "00时23分"
        },
        {
          "title": "北约秘书长吕特：与特朗普进行了非常坦率、公开的讨论。特朗普显然对北约感到失望。",
          "url": "https://wallstreetcn.com/livenews/3084630",
          "source": "华尔街见闻-快讯",
          "ranks": [
            15
          ],
          "is_new": false,
          "appearance_count": 1,
          "time_info": "08时08分"
        },
        {
          "title": "特朗普与吕特会面后再次抨击北约",
          "url": "https://flash.jin10.com/detail/20260409073755154800",
          "source": "金十数据",
          "ranks": [
            16
          ],
          "is_new": false,
          "appearance_count": 1,
          "time_info": "08时08分"
        },
        {
          "title": "美国总统特朗普：对美国而言，只有一组有意义、可接受的“要点”，我们将在闭门会议中进行讨论。",
          "url": "https://flash.jin10.com/detail/20260409000711248800",
          "source": "金十数据",
          "ranks": [
            17
          ],
          "is_new": false,
          "appearance_count": 1,
          "time_info": "00时23分"
        },
        {
          "title": "白宫：特朗普认为北约未通过“考验” 将与吕特讨论“退群”",
          "url": "https://flash.jin10.com/detail/20260409032129898800",
          "source": "金十数据",
          "ranks": [
            17
          ],
          "is_new": false,
          "appearance_count": 1,
          "time_info": "04时10分"
        },
        {
          "title": "美国总统特朗普：许多与美国/伊朗谈判毫无关系的人正在发送各种协议、清单和信件。在很多情况下，他们都是彻头彻尾的骗子、江湖术士，甚至更恶劣。",
          "url": "https://flash.jin10.com/detail/20260409000623381800",
          "source": "金十数据",
          "ranks": [
            18
          ],
          "is_new": false,
          "appearance_count": 1,
          "time_info": "00时23分"
        },
        {
          "title": "美国总统特朗普：北约在我们需要他们的时候不在，如果我们再次需要他们，他们也不会在。",
          "url": "https://flash.jin10.com/detail/20260409073318788800",
          "source": "金十数据",
          "ranks": [
            18
          ],
          "is_new": false,
          "appearance_count": 1,
          "time_info": "08时08分"
        },
        {
          "title": "特朗普：考虑与伊朗“合资经营”霍尔木兹海峡",
          "url": "https://wallstreetcn.com/livenews/3084464",
          "source": "华尔街见闻-快讯",
          "ranks": [
            18
          ],
          "is_new": false,
          "appearance_count": 1,
          "time_info": "00时23分"
        },
        {
          "title": "白宫新闻秘书莱维特：美国总统特朗普周二与以色列总理内塔尼亚胡进行了通话。",
          "url": "https://flash.jin10.com/detail/20260409014149272800",
          "source": "金十数据",
          "ranks": [
            19
          ],
          "is_new": false,
          "appearance_count": 1,
          "time_info": "02时21分"
        },
        {
          "title": "白宫新闻秘书莱维特：特朗普更关心结果而非言辞。",
          "url": "https://flash.jin10.com/detail/20260409014043785800",
          "source": "金十数据",
          "ranks": [
            20
          ],
          "is_new": false,
          "appearance_count": 1,
          "time_info": "02时21分"
        },
        {
          "title": "白宫证实特朗普已考虑退出北约",
          "url": "https://flash.jin10.com/detail/20260409023902796800",
          "source": "金十数据",
          "ranks": [
            20
          ],
          "is_new": false,
          "appearance_count": 1,
          "time_info": "03时28分"
        },
        {
          "title": "市场消息：北约秘书长吕特抵达白宫与特朗普会面。",
          "url": "https://flash.jin10.com/detail/20260409031408777800",
          "source": "金十数据",
          "ranks": [
            20
          ],
          "is_new": false,
          "appearance_count": 1,
          "time_info": "04时10分"
        },
        {
          "title": "美媒：特朗普考虑撤出部分北约盟国的美军",
          "url": "https://flash.jin10.com/detail/20260409042356816800",
          "source": "金十数据",
          "ranks": [
            20
          ],
          "is_new": false,
          "appearance_count": 1,
          "time_info": "05时13分"
        },
        {
          "title": "北约秘书长：特朗普对北约盟友的失望“很明显”",
          "url": "https://wallstreetcn.com/livenews/3084693",
          "source": "华尔街见闻-快讯",
          "ranks": [
            21
          ],
          "is_new": false,
          "appearance_count": 1,
          "time_info": "10时59分"
        },
        {
          "title": "白宫新闻秘书莱维特：美国总统特朗普派遣由美国副总统万斯率领的代表团赴巴基斯坦谈判。",
          "url": "https://flash.jin10.com/detail/20260409013855708800",
          "source": "金十数据",
          "ranks": [
            22
          ],
          "is_new": false,
          "appearance_count": 1,
          "time_info": "02时21分"
        },
        {
          "title": "特朗普不满北约：还记得格陵兰岛吗",
          "url": "https://wallstreetcn.com/livenews/3084653",
          "source": "华尔街见闻-快讯",
          "ranks": [
            23
          ],
          "is_new": false,
          "appearance_count": 1,
          "time_info": "09时31分"
        },
        {
          "title": "白宫新闻秘书莱维特：（就霍尔木兹海峡）美国总统特朗普将让伊朗为海峡保持开放负责。",
          "url": "https://flash.jin10.com/detail/20260409013805976800",
          "source": "金十数据",
          "ranks": [
            24
          ],
          "is_new": false,
          "appearance_count": 1,
          "time_info": "02时21分"
        },
        {
          "title": "报道：特朗普未反对以色列继续对抗真主党",
          "url": "https://wallstreetcn.com/livenews/3084458",
          "source": "华尔街见闻-快讯",
          "ranks": [
            24
          ],
          "is_new": false,
          "appearance_count": 1,
          "time_info": "00时23分"
        },
        {
          "title": "美国共和党参议员格雷厄姆：特朗普总统明白过去的领导人所忽视的，即伊朗绝不能拥有核武器。",
          "url": "https://flash.jin10.com/detail/20260409095703896800",
          "source": "金十数据",
          "ranks": [
            26
          ],
          "is_new": false,
          "appearance_count": 1,
          "time_info": "10时59分"
        },
        {
          "title": "特朗普说美媒披露的10项停战条款是“假新闻”",
          "url": "https://flash.jin10.com/detail/20260409110940415800",
          "source": "金十数据",
          "ranks": [
            26
          ],
          "is_new": false,
          "appearance_count": 1,
          "time_info": "12时00分"
        },
        {
          "title": "特朗普施压欧洲盟友：数日内必须提交具体的护航方案！",
          "url": "https://flash.jin10.com/detail/20260409135932294800",
          "source": "金十数据",
          "ranks": [
            26
          ],
          "is_new": false,
          "appearance_count": 1,
          "time_info": "14时28分"
        },
        {
          "title": "美国副总统万斯：特朗普曾提及过解除制裁事宜。他还谈到了经济合作之类的内容。但除非伊朗方面明确承诺停止任何接近制造核武器的活动，否则这种情况是不会发生的。",
          "url": "https://flash.jin10.com/detail/20260409040801394800",
          "source": "金十数据",
          "ranks": [
            27
          ],
          "is_new": false,
          "appearance_count": 1,
          "time_info": "05时13分"
        },
        {
          "title": "特朗普说美媒披露的停战条款是假新闻",
          "url": "https://s.weibo.com/weibo?q=%23%E7%89%B9%E6%9C%97%E6%99%AE%E8%AF%B4%E7%BE%8E%E5%AA%92%E6%8A%AB%E9%9C%B2%E7%9A%84%E5%81%9C%E6%88%98%E6%9D%A1%E6%AC%BE%E6%98%AF%E5%81%87%E6%96%B0%E9%97%BB%23&t=31&band_rank=27&Refer=top",
          "source": "微博",
          "ranks": [
            27
          ],
          "is_new": false,
          "appearance_count": 1,
          "time_info": "16时27分"
        },
        {
          "title": "因未获伊朗战争支持，美国总统特朗普考虑惩罚某些北约国家。",
          "url": "https://flash.jin10.com/detail/20260409040702671800",
          "source": "金十数据",
          "ranks": [
            28
          ],
          "is_new": false,
          "appearance_count": 1,
          "time_info": "05时13分"
        },
        {
          "title": "美媒：石油行业抵制特朗普的伊朗和平计划",
          "url": "https://flash.jin10.com/detail/20260409070539369800",
          "source": "金十数据",
          "ranks": [
            29
          ],
          "is_new": false,
          "appearance_count": 1,
          "time_info": "08时08分"
        },
        {
          "title": "特朗普：所有美国舰船、飞机和军事人员将继续留在伊朗周围",
          "url": "https://flash.jin10.com/detail/20260409115619215800",
          "source": "金十数据",
          "ranks": [
            29
          ],
          "is_new": false,
          "appearance_count": 1,
          "time_info": "12时54分"
        },
        {
          "title": "奥地利总统谈及中东局势，称：很高兴各方意识到，战争言论和升级行动无法解决冲突。 （美国总统特朗普）最近几天发出的威胁令人震惊。",
          "url": "https://wallstreetcn.com/livenews/3084452",
          "source": "华尔街见闻-快讯",
          "ranks": [
            30
          ],
          "is_new": false,
          "appearance_count": 1,
          "time_info": "00时23分"
        },
        {
          "title": "特朗普称美伊停火不包括黎巴嫩",
          "url": "https://s.weibo.com/weibo?q=%23%E7%89%B9%E6%9C%97%E6%99%AE%E7%A7%B0%E7%BE%8E%E4%BC%8A%E5%81%9C%E7%81%AB%E4%B8%8D%E5%8C%85%E6%8B%AC%E9%BB%8E%E5%B7%B4%E5%AB%A9%23&t=31&band_rank=30&Refer=top",
          "source": "微博",
          "ranks": [
            30
          ],
          "is_new": false,
          "appearance_count": 1,
          "time_info": "16时27分"
        }
      ]
    },
    {
      "keyword_group": "美股 A股 港股 大A 恒生科技 创业板 科创板",
      "match_count": 59,
      "titles": [
        {
          "title": "美伊停火提振全球市场，美股指大涨2%，半导体指数新高，油价创疫情来最大日跌幅",
          "url": "https://wallstreetcn.com/articles/3769443",
          "source": "华尔街见闻",
          "ranks": [
            1,
            5
          ],
          "is_new": false,
          "appearance_count": 18,
          "time_info": "[08时07分 ~ 18时23分]"
        },
        {
          "title": "美股收盘：三大指数均涨超2% 芯片股全线爆发、能源巨头重挫",
          "url": "https://www.cls.cn/detail/2338535",
          "source": "财联社热门",
          "ranks": [
            5,
            4,
            3
          ],
          "is_new": false,
          "appearance_count": 14,
          "time_info": "[07时12分 ~ 15时29分]"
        },
        {
          "title": "美伊谈判现逆转信号，美股抹平跌幅，盘后又见TACO，美股指期货大涨，油价大跳水，金银跳涨",
          "url": "https://wallstreetcn.com/articles/3769370",
          "source": "华尔街见闻",
          "ranks": [
            3
          ],
          "is_new": false,
          "appearance_count": 8,
          "time_info": "[00时23分 ~ 07时12分]"
        },
        {
          "title": "又现内幕交易？美伊停火前 神秘资金精准“空原油、多美股”",
          "url": "https://www.cls.cn/detail/2338764",
          "source": "财联社热门",
          "ranks": [
            13,
            8,
            5,
            4
          ],
          "is_new": false,
          "appearance_count": 10,
          "time_info": "[12时54分 ~ 18时23分]"
        },
        {
          "title": "伊朗战争反复冲击市场 美股交易强度创历史新高",
          "url": "https://www.cls.cn/detail/2338302",
          "source": "财联社热门",
          "ranks": [
            6,
            5,
            10,
            11,
            12
          ],
          "is_new": false,
          "appearance_count": 11,
          "time_info": "[00时23分 ~ 09时31分]"
        },
        {
          "title": "报复性反弹！美伊“停火两周”，美股开盘集体上涨，美光涨超8%，现货钯金涨超9%，油价创近六年最大跌幅",
          "url": "https://wallstreetcn.com/articles/3769443",
          "source": "华尔街见闻",
          "ranks": [
            2
          ],
          "is_new": false,
          "appearance_count": 6,
          "time_info": "[00时23分 ~ 05时13分]"
        },
        {
          "title": "A股",
          "url": "https://www.douyin.com/hot/2460150",
          "source": "抖音",
          "ranks": [
            10,
            17,
            20,
            14,
            15,
            21,
            24,
            23,
            22
          ],
          "is_new": false,
          "appearance_count": 15,
          "time_info": "[10时58分 ~ 18时23分]"
        },
        {
          "title": "“莫氏鸡煲”爆红出圈一鸡难求？ A股千亿巨头主动“送鸡”接流量",
          "url": "https://www.cls.cn/detail/2338241",
          "source": "财联社热门",
          "ranks": [
            13,
            12,
            10,
            11
          ],
          "is_new": false,
          "appearance_count": 9,
          "time_info": "[00时23分 ~ 08时08分]"
        },
        {
          "title": "【焦点复盘】创业板指涨近6%终结5连阴，全市场超300股涨逾9%，两市放量超8000亿",
          "url": "https://www.cls.cn/detail/2338025",
          "source": "财联社热门",
          "ranks": [
            2,
            3
          ],
          "is_new": false,
          "appearance_count": 4,
          "time_info": "[00时23分 ~ 03时28分]"
        },
        {
          "title": "美股三大指数大幅高开 纳指涨3.65%",
          "url": "https://www.baidu.com/s?wd=%E7%BE%8E%E8%82%A1%E4%B8%89%E5%A4%A7%E6%8C%87%E6%95%B0%E5%A4%A7%E5%B9%85%E9%AB%98%E5%BC%80+%E7%BA%B3%E6%8C%87%E6%B6%A83.65%25",
          "source": "百度热搜",
          "ranks": [
            12
          ],
          "is_new": false,
          "appearance_count": 8,
          "time_info": "[00时23分 ~ 07时12分]"
        },
        {
          "title": "美伊停火提振全球市场，美股指大涨2%，半导体指数新高，油价创六年最大单日跌幅",
          "url": "https://wallstreetcn.com/articles/3769443",
          "source": "华尔街见闻",
          "ranks": [
            2
          ],
          "is_new": false,
          "appearance_count": 2,
          "time_info": "[06时11分 ~ 07时12分]"
        },
        {
          "title": "金十数据整理：A股盘前市场要闻速递（2026-04-09）",
          "url": "https://flash.jin10.com/detail/20260409090413176800",
          "source": "金十数据",
          "ranks": [
            1
          ],
          "is_new": false,
          "appearance_count": 1,
          "time_info": "09时31分"
        },
        {
          "title": "A股煤化工板块短线拉升，诚志股份涨停，金牛化工、金煤科技、鲁西化工、宝丰能源、华谊集团等跟涨。",
          "url": "https://flash.jin10.com/detail/20260409130945861800",
          "source": "金十数据",
          "ranks": [
            1
          ],
          "is_new": false,
          "appearance_count": 1,
          "time_info": "13时34分"
        },
        {
          "title": "A股光纤概念反复活跃，长江通信触及涨停创新高，光迅科技此前封板，大族激光、长飞光纤、致尚科技涨幅居前。",
          "url": "https://flash.jin10.com/detail/20260409103956226800",
          "source": "金十数据",
          "ranks": [
            2
          ],
          "is_new": false,
          "appearance_count": 1,
          "time_info": "10时59分"
        },
        {
          "title": "港股化工板块走强，中国三江化工(02198.HK)涨超9%，中国旭阳集团(01907.HK)涨超5%，国恩科技(0278.HK)、中伟新材(02579.HK)等跟涨。",
          "url": "https://flash.jin10.com/detail/20260409141906138800",
          "source": "金十数据",
          "ranks": [
            2
          ],
          "is_new": false,
          "appearance_count": 1,
          "time_info": "14时28分"
        },
        {
          "title": "贝莱德投资官：美股盈利预期过于乐观",
          "url": "https://flash.jin10.com/detail/20260409175218304800",
          "source": "金十数据",
          "ranks": [
            2
          ],
          "is_new": true,
          "appearance_count": 1,
          "time_info": "18时23分"
        },
        {
          "title": "金十数据整理：每日港股市场要闻速递（2026-04-09）",
          "url": "https://flash.jin10.com/detail/20260409090253771800",
          "source": "金十数据",
          "ranks": [
            3
          ],
          "is_new": false,
          "appearance_count": 1,
          "time_info": "09时31分"
        },
        {
          "title": "中国上证综指4月9日（周四）收盘下跌28.83点，跌幅：0.72%，报3966.17点；<br/>中国深证成指4月9日（周四）收盘下跌46.23点，跌幅：0.33%，报13996.27点；<br/>中国沪深300指数4月9日（周四）收盘下跌29.33点，跌幅：0.64%，报4566.22点；<br/>中国创业板指数4月9日（周四）收盘下跌24.31点，跌幅：0.73%，报3323.3点；<br/>中国科创50指数4月9日（周四）收盘下跌8.74点，跌幅：0.65%，报1343.95点。",
          "url": "https://flash.jin10.com/detail/20260409150248756800",
          "source": "金十数据",
          "ranks": [
            4
          ],
          "is_new": false,
          "appearance_count": 1,
          "time_info": "15时29分"
        },
        {
          "title": "港股恒指强力反弹背后 阿里巴巴卖空股数激增近130%",
          "url": "https://www.cls.cn/detail/2338812",
          "source": "财联社热门",
          "ranks": [
            11,
            9,
            8
          ],
          "is_new": false,
          "appearance_count": 5,
          "time_info": "[16时27分 ~ 18时23分]"
        },
        {
          "title": "A股收盘：全市场近4300只个股飘绿",
          "url": "https://www.baidu.com/s?wd=A%E8%82%A1%E6%94%B6%E7%9B%98%EF%BC%9A%E5%85%A8%E5%B8%82%E5%9C%BA%E8%BF%914300%E5%8F%AA%E4%B8%AA%E8%82%A1%E9%A3%98%E7%BB%BF",
          "source": "百度热搜",
          "ranks": [
            24,
            23
          ],
          "is_new": false,
          "appearance_count": 5,
          "time_info": "[16时27分 ~ 18时23分]"
        },
        {
          "title": "上证指数开盘报3967.63点，跌0.69%。 深证成指开盘报13928.43点，跌0.81%。 创业板指开盘报3316.29点，跌0.94%。 沪深300开盘报4562.67点，跌0.72%。 科创50开盘报1335.29点，跌1.29%。 中证500开盘报7865.21点，跌1.01%。 中证1000开盘报7881.80点，跌0.93%。",
          "url": "https://wallstreetcn.com/livenews/3084681",
          "source": "华尔街见闻-快讯",
          "ranks": [
            1,
            25
          ],
          "is_new": false,
          "appearance_count": 2,
          "time_info": "[09时31分 ~ 10时59分]"
        },
        {
          "title": "港股大模型股走高，智谱涨近14%，MINIMAX涨超9%。",
          "url": "https://wallstreetcn.com/livenews/3084734",
          "source": "华尔街见闻-快讯",
          "ranks": [
            1,
            17
          ],
          "is_new": false,
          "appearance_count": 2,
          "time_info": "[10时59分 ~ 12时00分]"
        },
        {
          "title": "恒生指数主连夜盘收跌0.34%，报25859点。 恒生科技指数主连夜盘收跌0.28%，报4928点。",
          "url": "https://wallstreetcn.com/livenews/3084542",
          "source": "华尔街见闻-快讯",
          "ranks": [
            4,
            13
          ],
          "is_new": false,
          "appearance_count": 2,
          "time_info": "[03时28分 ~ 04时10分]"
        },
        {
          "title": "恒指低开0.53%，报25756.41点；恒生科技指数跌1.11%。阿里巴巴、快手、华虹半导体等跌超2%。",
          "url": "https://wallstreetcn.com/livenews/3084678",
          "source": "华尔街见闻-快讯",
          "ranks": [
            4,
            28
          ],
          "is_new": false,
          "appearance_count": 2,
          "time_info": "[09时31分 ~ 10时59分]"
        },
        {
          "title": "上证指数早盘收报3965.70点，跌0.73%。 深证成指早盘收报13999.55点，跌0.31%。 创业板指早盘收报3325.29点，跌0.67%。 沪深300早盘收报4566.22点，跌0.64%。 科创50早盘收报1350.03点，跌0.20%。 中证500早盘收报7902.96点，跌0.53%。 中证1000早盘收报7918.78点，跌0.46%。",
          "url": "https://wallstreetcn.com/livenews/3084753",
          "source": "华尔街见闻-快讯",
          "ranks": [
            6,
            20,
            29
          ],
          "is_new": false,
          "appearance_count": 3,
          "time_info": "[12时00分 ~ 13时34分]"
        },
        {
          "title": "美股三大指数均涨超2% 能源巨头重挫",
          "url": "https://www.baidu.com/s?wd=%E7%BE%8E%E8%82%A1%E4%B8%89%E5%A4%A7%E6%8C%87%E6%95%B0%E5%9D%87%E6%B6%A8%E8%B6%852%25+%E8%83%BD%E6%BA%90%E5%B7%A8%E5%A4%B4%E9%87%8D%E6%8C%AB",
          "source": "百度热搜",
          "ranks": [
            15
          ],
          "is_new": false,
          "appearance_count": 3,
          "time_info": "[08时07分 ~ 09时31分]"
        },
        {
          "title": "A股稀土永磁板块午后再度拉升，英洛华直线涨停，华宏科技此前涨停，九菱科技、华新环保、新莱福、中稀有色、中科磁业跟涨。",
          "url": "https://wallstreetcn.com/livenews/3084785",
          "source": "华尔街见闻-快讯",
          "ranks": [
            6,
            24
          ],
          "is_new": false,
          "appearance_count": 2,
          "time_info": "[13时34分 ~ 14时28分]"
        },
        {
          "title": "港股收盘：恒生指数收跌0.54%，恒生科技指数收跌2.06%。新能源汽车股下挫，小鹏跌超5%，比亚迪股份跌超4%。科网股走低，快手跌逾3%。",
          "url": "https://wallstreetcn.com/livenews/3084924",
          "source": "华尔街见闻-快讯",
          "ranks": [
            8,
            29
          ],
          "is_new": false,
          "appearance_count": 2,
          "time_info": "[16时27分 ~ 17时25分]"
        },
        {
          "title": "周三（4月8日），美股行业ETF普遍收涨，半导体ETF涨5.76%，全球航空业ETF涨5.65%，全球科技股指数ETF、科技行业ETF、区域银行ETF、银行业ETF、可选消费ETF、金融业ETF、网络股指数ETF至少涨2.46%，能源业ETF则收跌3.51%。",
          "url": "https://wallstreetcn.com/livenews/3084565",
          "source": "华尔街见闻-快讯",
          "ranks": [
            10,
            27
          ],
          "is_new": false,
          "appearance_count": 2,
          "time_info": "[05时13分 ~ 06时11分]"
        },
        {
          "title": "A股开盘：沪指跌0.69% 贵金属领跌",
          "url": "https://www.baidu.com/s?wd=A%E8%82%A1%E5%BC%80%E7%9B%98%EF%BC%9A%E6%B2%AA%E6%8C%87%E8%B7%8C0.69%25+%E8%B4%B5%E9%87%91%E5%B1%9E%E9%A2%86%E8%B7%8C",
          "source": "百度热搜",
          "ranks": [
            16
          ],
          "is_new": false,
          "appearance_count": 2,
          "time_info": "[10时58分 ~ 10时59分]"
        },
        {
          "title": "港股收跌0.54% 新能源汽车股下挫",
          "url": "https://www.baidu.com/s?wd=%E6%B8%AF%E8%82%A1%E6%94%B6%E8%B7%8C0.54%25+%E6%96%B0%E8%83%BD%E6%BA%90%E6%B1%BD%E8%BD%A6%E8%82%A1%E4%B8%8B%E6%8C%AB",
          "source": "百度热搜",
          "ranks": [
            17
          ],
          "is_new": false,
          "appearance_count": 2,
          "time_info": "[17时24分 ~ 17时25分]"
        },
        {
          "title": "美股三大指数收涨超2%",
          "url": "https://www.toutiao.com/trending/7626528667786579498/",
          "source": "今日头条",
          "ranks": [
            27
          ],
          "is_new": false,
          "appearance_count": 2,
          "time_info": "[08时07分 ~ 08时08分]"
        },
        {
          "title": "A股三大股指收跌 两市成交2.1万亿",
          "url": "https://www.toutiao.com/trending/7625865343887245362/",
          "source": "今日头条",
          "ranks": [
            28
          ],
          "is_new": false,
          "appearance_count": 2,
          "time_info": "[18时22分 ~ 18时23分]"
        },
        {
          "title": "港股绿茶集团(06831.HK)盘中跌超10%，公司早间公告，主要股东PartnersGroupGourmetHouseLimited计划清仓式减持约15.96%公司股份，不再持有任何股份，并将不再为公司股东。",
          "url": "https://flash.jin10.com/detail/20260409150201384800",
          "source": "金十数据",
          "ranks": [
            7
          ],
          "is_new": false,
          "appearance_count": 1,
          "time_info": "15时29分"
        },
        {
          "title": "A股光纤概念再度活跃，特发信息午后涨停，长江通信此前封板，长飞光纤涨超7%，股价均创历史新高，汇源通信5连板，永鼎股份、光电股份、通光线缆等涨幅靠前。",
          "url": "https://wallstreetcn.com/livenews/3084819",
          "source": "华尔街见闻-快讯",
          "ranks": [
            7
          ],
          "is_new": false,
          "appearance_count": 1,
          "time_info": "14时28分"
        },
        {
          "title": "港股光通信板块持续走强，汇聚科技(01729.HK)涨超8%，长飞光纤光缆(06869.HK)涨超5%，剑桥科技(06166.HK)、华虹半导体(01347.HK)等跟涨。",
          "url": "https://flash.jin10.com/detail/20260409102621732800",
          "source": "金十数据",
          "ranks": [
            8
          ],
          "is_new": false,
          "appearance_count": 1,
          "time_info": "10时59分"
        },
        {
          "title": "周三（4月8日），存储芯片与硬件供应链指数涨8.08%，报125.83点，跳空高开、迅速刷新日高至127.77点，美股开盘后90分钟内呈现出冲高回落走势。 信息科技指数涨4.61%，人工智能（AI）赢家指数涨4.96%；AI软件先驱指数跌1.04%。",
          "url": "https://wallstreetcn.com/livenews/3084589",
          "source": "华尔街见闻-快讯",
          "ranks": [
            8
          ],
          "is_new": false,
          "appearance_count": 1,
          "time_info": "06时11分"
        },
        {
          "title": "美股七巨头收盘播报｜周三（4月8日），美国科技股七巨头（Magnificent 7）指数涨2.52%，报191.61点，跳空高开至194.23点之后快速回吐涨幅，绝大部分时间交投于盘初出现的日低190.68点附近，整体呈现出W形走势。 “超大”市值科技股指数涨2.61%，报366.44点。",
          "url": "https://wallstreetcn.com/livenews/3084588",
          "source": "华尔街见闻-快讯",
          "ranks": [
            9
          ],
          "is_new": false,
          "appearance_count": 1,
          "time_info": "06时11分"
        },
        {
          "title": "恒生科技指数跌幅扩大至2%。",
          "url": "https://wallstreetcn.com/livenews/3084870",
          "source": "华尔街见闻-快讯",
          "ranks": [
            9
          ],
          "is_new": false,
          "appearance_count": 1,
          "time_info": "15时29分"
        },
        {
          "title": "在美股时段交易的费城金银指数收涨3.28%，报399.65点。 在全球市场全天交易的纽约证交所ARCA金矿开采商指数涨4.03%，报2713.10点。 在美股时段交易的原材料指数收涨3.30%，金属与矿业指数收涨4.68%。",
          "url": "https://wallstreetcn.com/livenews/3084587",
          "source": "华尔街见闻-快讯",
          "ranks": [
            10
          ],
          "is_new": false,
          "appearance_count": 1,
          "time_info": "06时11分"
        },
        {
          "title": "中信建投：若美股出现又一波下跌 建议积极增持",
          "url": "https://wallstreetcn.com/livenews/3084639",
          "source": "华尔街见闻-快讯",
          "ranks": [
            10
          ],
          "is_new": false,
          "appearance_count": 1,
          "time_info": "08时08分"
        },
        {
          "title": "A股午评：三大股指水下盘整 PCB、CPO等算力基建板块维持强势",
          "url": "https://flash.jin10.com/detail/20260409113353760800",
          "source": "金十数据",
          "ranks": [
            12
          ],
          "is_new": false,
          "appearance_count": 1,
          "time_info": "12时00分"
        },
        {
          "title": "美股盘前，科技股普跌，英特尔跌超1.5%；存储股持续下挫，美光科技跌近2%，闪迪跌约1%。",
          "url": "https://wallstreetcn.com/livenews/3084915",
          "source": "华尔街见闻-快讯",
          "ranks": [
            12
          ],
          "is_new": false,
          "appearance_count": 1,
          "time_info": "16时27分"
        },
        {
          "title": "美股股指期货周四开盘微跌，WTI原油微涨，现货黄金高开0.15%。",
          "url": "https://flash.jin10.com/detail/20260409060126125800",
          "source": "金十数据",
          "ranks": [
            14
          ],
          "is_new": false,
          "appearance_count": 1,
          "time_info": "07时12分"
        },
        {
          "title": "周三（4月8日），彭博电动汽车价格回报指数涨3.79%，报3742.59点，亚太盘初以来持续走高，北京时间21:30美股开盘时跳空至3762.34点刷新日高，随后持续高位窄幅震荡。 成分股中，小马智行涨10.2%，MP材料涨9.4%，淡水河谷印尼公司收涨8.30%，地平线H股收涨8.30%，阿内卡矿业股份收涨7.78%，禾赛科技涨7.5%，沃尔沃汽车集团欧股收涨7.5%，四只成分股收跌，L&F有限公司韩国股价收跌0.49%，LG新能源收跌0.61%，特斯拉跌超1%，雅迪集团控股H股收跌4.52%。",
          "url": "https://wallstreetcn.com/livenews/3084561",
          "source": "华尔街见闻-快讯",
          "ranks": [
            14
          ],
          "is_new": false,
          "appearance_count": 1,
          "time_info": "05时13分"
        },
        {
          "title": "港股AI应用板块午后持续走弱，金蝶国际(00268.HK)跌超7%，金山软件(03888.HK)2跌超4%，阜博集团(03738.HK)、涂鸦智能(02391.HK)等跟跌。",
          "url": "https://flash.jin10.com/detail/20260409154818939800",
          "source": "金十数据",
          "ranks": [
            16
          ],
          "is_new": false,
          "appearance_count": 1,
          "time_info": "16时27分"
        },
        {
          "title": "港股汽车股持续走强，吉利汽车(00175.HK)、奇瑞汽车(09973.HK)涨超4%，蔚来-SW(09866.HK)涨超3%，零跑汽车(09863.HK)等跟涨。",
          "url": "https://flash.jin10.com/detail/20260409100444510800",
          "source": "金十数据",
          "ranks": [
            19
          ],
          "is_new": false,
          "appearance_count": 1,
          "time_info": "10时59分"
        },
        {
          "title": "港股汽车股午后持续回落，小鹏集团(09868.HK)跌超5%，比亚迪股份(01211.HK)跌超4%，赛力斯(09927.HK)、理想汽车(02015.HK)等跟跌。",
          "url": "https://flash.jin10.com/detail/20260409140106873800",
          "source": "金十数据",
          "ranks": [
            19
          ],
          "is_new": false,
          "appearance_count": 1,
          "time_info": "14时28分"
        },
        {
          "title": "周三（4月8日），美股降息赢家指数涨4.42%，报90.26点。 “特朗普关税输家”指数涨4.03%，报101.50点；“特朗普金融指数”涨4.18%，报158.68点。 散户抱团概念股指数/迷因股（meme stock）指数涨8.80%，报125.83点。",
          "url": "https://wallstreetcn.com/livenews/3084602",
          "source": "华尔街见闻-快讯",
          "ranks": [
            19
          ],
          "is_new": false,
          "appearance_count": 1,
          "time_info": "07时12分"
        },
        {
          "title": "深成指、创业板指均跌超1%，沪指跌0.77%，贵金属、光伏设备、民航机场、AI应用等方向跌幅居前，沪深京三市下跌个股超4200只。",
          "url": "https://wallstreetcn.com/livenews/3084698",
          "source": "华尔街见闻-快讯",
          "ranks": [
            19
          ],
          "is_new": false,
          "appearance_count": 1,
          "time_info": "10时59分"
        },
        {
          "title": "美股三大股指期货短线走低，纳指期货跌幅扩大至0.4%，标普500指数期货跌0.41%，道指期货跌0.38%。",
          "url": "https://wallstreetcn.com/livenews/3084906",
          "source": "华尔街见闻-快讯",
          "ranks": [
            19
          ],
          "is_new": false,
          "appearance_count": 1,
          "time_info": "16时27分"
        },
        {
          "title": "如何看待A股再现放量大涨",
          "url": "https://www.toutiao.com/trending/7625981091035676708/",
          "source": "今日头条",
          "ranks": [
            20
          ],
          "is_new": false,
          "appearance_count": 1,
          "time_info": "00时23分"
        },
        {
          "title": "深交所：港股通标的证券名单发生调整并自2026年04月09日起生效，调入希迪智驾。",
          "url": "https://flash.jin10.com/detail/20260409084437653800",
          "source": "金十数据",
          "ranks": [
            20
          ],
          "is_new": false,
          "appearance_count": 1,
          "time_info": "09时31分"
        },
        {
          "title": "港股午评：恒指缩量调整小幅收跌 科网股回调盘整",
          "url": "https://flash.jin10.com/detail/20260409121132018800",
          "source": "金十数据",
          "ranks": [
            21
          ],
          "is_new": false,
          "appearance_count": 1,
          "time_info": "12时54分"
        },
        {
          "title": "上证指数收报3966.17点，跌0.72%。 深证成指收报13996.27点，跌0.33%。 创业板指收报3323.30点，跌0.73%。 沪深300收报4566.22点，跌0.64%。 科创50收报1343.95点，跌0.65%。 中证500收报7898.63点，跌0.59%。 中证1000收报7921.45点，跌0.43%。",
          "url": "https://wallstreetcn.com/livenews/3084854",
          "source": "华尔街见闻-快讯",
          "ranks": [
            23
          ],
          "is_new": false,
          "appearance_count": 1,
          "time_info": "15时29分"
        },
        {
          "title": "A股存储芯片概念探底后震荡回升，大为股份走出2连板，商络电子、矽电股份、西测测试、德明利、普冉股份等冲高。",
          "url": "https://flash.jin10.com/detail/20260409100110184800",
          "source": "金十数据",
          "ranks": [
            24
          ],
          "is_new": false,
          "appearance_count": 1,
          "time_info": "10时59分"
        },
        {
          "title": "A股铜缆高速连接概念拉升，航天电器涨停，陕西华达、中富电路、凯旺科技、胜蓝股份等涨幅居前。",
          "url": "https://flash.jin10.com/detail/20260409095719166800",
          "source": "金十数据",
          "ranks": [
            25
          ],
          "is_new": false,
          "appearance_count": 1,
          "time_info": "10时59分"
        },
        {
          "title": "A股稀土永磁板块短线拉升，华宏科技涨停，九菱科技、祥明智能、中稀有色、华新环保、奔朗新材等纷纷走高。",
          "url": "https://flash.jin10.com/detail/20260409095413922800",
          "source": "金十数据",
          "ranks": [
            28
          ],
          "is_new": false,
          "appearance_count": 1,
          "time_info": "10时59分"
        },
        {
          "title": "金十图示：2026年04月08日（周三）美股热门股票行情一览（美股收盘）",
          "url": "https://flash.jin10.com/detail/20260409040608867800",
          "source": "金十数据",
          "ranks": [
            30
          ],
          "is_new": false,
          "appearance_count": 1,
          "time_info": "05时13分"
        }
      ]
    },
    {
      "keyword_group": "原油",
      "match_count": 31,
      "titles": [
        {
          "title": "伊朗要求以加密货币支付霍尔木兹海峡通行费，每桶原油 1 美元，对航运成本有多大影响？为何要用加密货币？",
          "url": "https://www.zhihu.com/question/2025530652930435004",
          "source": "知乎",
          "ranks": [
            11
          ],
          "is_new": false,
          "appearance_count": 8,
          "time_info": "[14时27分 ~ 18时23分]"
        },
        {
          "title": "机构：物流瓶颈制约中东原油复产节奏 需对海峡安全通行建立信心",
          "url": "https://flash.jin10.com/detail/20260409001806144800",
          "source": "金十数据",
          "ranks": [
            4
          ],
          "is_new": false,
          "appearance_count": 1,
          "time_info": "00时23分"
        },
        {
          "title": "美国白宫：匈牙利能源公司MOL集团从美国及美国企业购入51万吨原油，价值5亿美元。",
          "url": "https://wallstreetcn.com/livenews/3084481",
          "source": "华尔街见闻-快讯",
          "ranks": [
            1,
            21
          ],
          "is_new": false,
          "appearance_count": 2,
          "time_info": "[00时23分 ~ 01时22分]"
        },
        {
          "title": "EIA年度能源展望报告：预计美国原油产量将在2027年增长约1%，达到创纪录的每天1362万桶。",
          "url": "https://flash.jin10.com/detail/20260409030902302800",
          "source": "金十数据",
          "ranks": [
            2,
            23
          ],
          "is_new": false,
          "appearance_count": 2,
          "time_info": "[03时28分 ~ 04时10分]"
        },
        {
          "title": "WTI原油期货涨幅扩大至4%，报98.2美元/桶。",
          "url": "https://wallstreetcn.com/livenews/3084680",
          "source": "华尔街见闻-快讯",
          "ranks": [
            2,
            26
          ],
          "is_new": false,
          "appearance_count": 2,
          "time_info": "[09时31分 ~ 10时59分]"
        },
        {
          "title": "EIA年度能源展望报告：到2050年，美国原油产量预计将介于每天1240万至1270万桶之间，而2025年为每天1360万桶。",
          "url": "https://flash.jin10.com/detail/20260409030146284800",
          "source": "金十数据",
          "ranks": [
            7,
            28
          ],
          "is_new": false,
          "appearance_count": 2,
          "time_info": "[03时28分 ~ 04时10分]"
        },
        {
          "title": "美国政府：美国原油产量将在2030年代中期出现下降",
          "url": "https://wallstreetcn.com/livenews/3084544",
          "source": "华尔街见闻-快讯",
          "ranks": [
            8,
            27
          ],
          "is_new": false,
          "appearance_count": 2,
          "time_info": "[04时10分 ~ 05时13分]"
        },
        {
          "title": "上期所原油期货2605合约夜盘收跌4.41%，报635.10元人民币/桶。 沪金夜盘收跌0.24%，沪银收涨1.45%。",
          "url": "https://wallstreetcn.com/livenews/3084531",
          "source": "华尔街见闻-快讯",
          "ranks": [
            11,
            20
          ],
          "is_new": false,
          "appearance_count": 2,
          "time_info": "[03时28分 ~ 04时10分]"
        },
        {
          "title": "WTI原油日内涨超1.00%，现报97.65美元/桶。",
          "url": "https://flash.jin10.com/detail/20260409062158734800",
          "source": "金十数据",
          "ranks": [
            7
          ],
          "is_new": false,
          "appearance_count": 1,
          "time_info": "07时12分"
        },
        {
          "title": "高盛：如果霍尔木兹海峡再关闭一个月，到2026年底，布伦特原油的平均价格将超过每桶100美元。",
          "url": "https://flash.jin10.com/detail/20260409171101878800",
          "source": "金十数据",
          "ranks": [
            7
          ],
          "is_new": false,
          "appearance_count": 1,
          "time_info": "17时25分"
        },
        {
          "title": "EIA年度能源展望报告：预计布伦特原油价格到2030年将低于每桶70美元，到2030年代末则将高于75美元。",
          "url": "https://flash.jin10.com/detail/20260409030129500800",
          "source": "金十数据",
          "ranks": [
            8
          ],
          "is_new": false,
          "appearance_count": 1,
          "time_info": "03时28分"
        },
        {
          "title": "美国白宫：匈牙利能源公司MOL集团从美国及美国企业购入51万吨原油，价值5亿美元。",
          "url": "https://flash.jin10.com/detail/20260409001536850800",
          "source": "金十数据",
          "ranks": [
            9
          ],
          "is_new": false,
          "appearance_count": 1,
          "time_info": "00时23分"
        },
        {
          "title": "澳新银行：石油供应中断已显著收紧全球原油供需平衡，市场正迅速从年初的供应过剩转为大幅短缺。",
          "url": "https://flash.jin10.com/detail/20260409130200734800",
          "source": "金十数据",
          "ranks": [
            9
          ],
          "is_new": false,
          "appearance_count": 1,
          "time_info": "13时34分"
        },
        {
          "title": "EIA年度能源展望报告：美国原油产量将保持相对稳定，到2050年将小幅下降。",
          "url": "https://flash.jin10.com/detail/20260409025941762800",
          "source": "金十数据",
          "ranks": [
            10
          ],
          "is_new": false,
          "appearance_count": 1,
          "time_info": "03时28分"
        },
        {
          "title": "美国原油期货收跌超16.4%，取暖油期货跌约15%",
          "url": "https://wallstreetcn.com/livenews/3084532",
          "source": "华尔街见闻-快讯",
          "ranks": [
            10
          ],
          "is_new": false,
          "appearance_count": 1,
          "time_info": "03时28分"
        },
        {
          "title": "早盘开盘，国内期货主力合约涨跌不一，集运欧线涨超4%，豆一涨超2%，国际铜、钯涨超1%。跌幅方面，甲醇跌超5%，乙二醇、丙烯、低硫燃料油（LU）、液化气跌超3%，聚丙烯、对二甲苯、SC原油、瓶片跌近3%。",
          "url": "https://flash.jin10.com/detail/20260409090002905800",
          "source": "金十数据",
          "ranks": [
            11
          ],
          "is_new": false,
          "appearance_count": 1,
          "time_info": "09时31分"
        },
        {
          "title": "商品期货开盘，集运欧线主力合约涨近5%，豆一涨超2%，国际铜、钯涨超1%。甲醇跌5%，乙二醇、丙烯、LU燃油、液化气跌超3%，聚丙烯、原油跌超2%。",
          "url": "https://wallstreetcn.com/livenews/3084667",
          "source": "华尔街见闻-快讯",
          "ranks": [
            11
          ],
          "is_new": false,
          "appearance_count": 1,
          "time_info": "09时31分"
        },
        {
          "title": "午盘收盘，国内期货主力合约跌多涨少，碳酸锂跌超4%，乙二醇、多晶硅、SC原油、烧碱、甲醇、焦煤、液化气、PVC跌超3%，塑料、铁矿石、锰硅跌超2%。涨幅方面，豆一、菜籽涨超4%，集运欧线涨超3%，红枣涨超2%，钯涨超1%。",
          "url": "https://flash.jin10.com/detail/20260409150104936800",
          "source": "金十数据",
          "ranks": [
            12
          ],
          "is_new": false,
          "appearance_count": 1,
          "time_info": "15时29分"
        },
        {
          "title": "布伦特原油日内涨幅达1.00%，现报95.43美元/桶。",
          "url": "https://flash.jin10.com/detail/20260409085458554800",
          "source": "金十数据",
          "ranks": [
            13
          ],
          "is_new": false,
          "appearance_count": 1,
          "time_info": "09时31分"
        },
        {
          "title": "布油、WTI原油期货日内双双涨超3%。",
          "url": "https://wallstreetcn.com/livenews/3084663",
          "source": "华尔街见闻-快讯",
          "ranks": [
            13
          ],
          "is_new": false,
          "appearance_count": 1,
          "time_info": "09时31分"
        },
        {
          "title": "布伦特原油跌幅收窄至8%，现报94.64美元/桶。",
          "url": "https://flash.jin10.com/detail/20260409032407469800",
          "source": "金十数据",
          "ranks": [
            15
          ],
          "is_new": false,
          "appearance_count": 1,
          "time_info": "04时10分"
        },
        {
          "title": "嘉实原油LOF：将于2026年4月10日开市起至当日10:30停牌，自2026年4月10日10:30复牌；停牌期间，本基金赎回业务照常办理。",
          "url": "https://flash.jin10.com/detail/20260409170350801800",
          "source": "金十数据",
          "ranks": [
            18
          ],
          "is_new": false,
          "appearance_count": 1,
          "time_info": "17时25分"
        },
        {
          "title": "加拿大原油运往墨西哥湾沿岸的利润创两年最大",
          "url": "https://flash.jin10.com/detail/20260409031614763800",
          "source": "金十数据",
          "ranks": [
            19
          ],
          "is_new": false,
          "appearance_count": 1,
          "time_info": "04时10分"
        },
        {
          "title": "120万桶原油“海上漂流”，印尼扣押的伊朗超级油轮身价大涨！",
          "url": "https://flash.jin10.com/detail/20260409124326601800",
          "source": "金十数据",
          "ranks": [
            19
          ],
          "is_new": false,
          "appearance_count": 1,
          "time_info": "13时34分"
        },
        {
          "title": "美国原油期货收跌16.4%，取暖油期货跌约15%，中东原油期货重挫18.7%",
          "url": "https://wallstreetcn.com/livenews/3084532",
          "source": "华尔街见闻-快讯",
          "ranks": [
            19
          ],
          "is_new": false,
          "appearance_count": 1,
          "time_info": "04时10分"
        },
        {
          "title": "周四亚太盘初，WTI原油日内涨幅达2.5%，报96.85美元/桶。 纽约金日内跌幅达0.5%，报4746.8美元/盎司。 三大股指期货至多跌0.1%。",
          "url": "https://wallstreetcn.com/livenews/3084601",
          "source": "华尔街见闻-快讯",
          "ranks": [
            20
          ],
          "is_new": false,
          "appearance_count": 1,
          "time_info": "07时12分"
        },
        {
          "title": "EIA：美国原油产量将在2030年代中期出现下降",
          "url": "https://flash.jin10.com/detail/20260409031045571800",
          "source": "金十数据",
          "ranks": [
            21
          ],
          "is_new": false,
          "appearance_count": 1,
          "time_info": "04时10分"
        },
        {
          "title": "SC原油主力合约日内大跌4.00%，现报637.50元/桶。",
          "url": "https://flash.jin10.com/detail/20260409100332974800",
          "source": "金十数据",
          "ranks": [
            21
          ],
          "is_new": false,
          "appearance_count": 1,
          "time_info": "10时59分"
        },
        {
          "title": "原油LOF易方达：将于2026年4月10日开市起至当日10:30停牌，自2026年4月10日10:30复牌；停牌期间，本基金赎回业务照常办理。",
          "url": "https://flash.jin10.com/detail/20260409170255307800",
          "source": "金十数据",
          "ranks": [
            21
          ],
          "is_new": false,
          "appearance_count": 1,
          "time_info": "17时25分"
        },
        {
          "title": "商品期货收盘，碳酸锂主力合约跌超4%，乙二醇、多晶硅、原油、烧碱、液化气、甲醇、焦煤跌超3%。豆一涨超4%，集运欧线涨3%，红枣涨超2%。",
          "url": "https://wallstreetcn.com/livenews/3084852",
          "source": "华尔街见闻-快讯",
          "ranks": [
            24
          ],
          "is_new": false,
          "appearance_count": 1,
          "time_info": "15时29分"
        },
        {
          "title": "高盛：如果霍尔木兹海峡再关闭一个月 布伦特原油均价料超过100美元",
          "url": "https://wallstreetcn.com/livenews/3084844",
          "source": "华尔街见闻-快讯",
          "ranks": [
            30
          ],
          "is_new": false,
          "appearance_count": 1,
          "time_info": "15时29分"
        }
      ]
    },
    {
      "keyword_group": "美债 国债",
      "match_count": 30,
      "titles": [
        {
          "title": "日本财务大臣片山皋月：（在被问及是否延长政府债务期限时）根据市场需求制定日本国债发行计划至关重要。",
          "url": "https://flash.jin10.com/detail/20260409103925219800",
          "source": "金十数据",
          "ranks": [
            3
          ],
          "is_new": false,
          "appearance_count": 1,
          "time_info": "10时59分"
        },
        {
          "title": "日本拍卖5年期国债，认购倍数3.58，过去12个月均值为3.49。",
          "url": "https://wallstreetcn.com/livenews/3084757",
          "source": "华尔街见闻-快讯",
          "ranks": [
            4,
            18,
            27
          ],
          "is_new": false,
          "appearance_count": 3,
          "time_info": "[12时00分 ~ 13时34分]"
        },
        {
          "title": "澳大利亚国债价格下跌，10年期澳债收益率悉尼盘初涨7个基点。",
          "url": "https://wallstreetcn.com/livenews/3084620",
          "source": "华尔街见闻-快讯",
          "ranks": [
            3,
            22
          ],
          "is_new": false,
          "appearance_count": 2,
          "time_info": "[07时12分 ~ 08时08分]"
        },
        {
          "title": "中国即将发行或正在发行的国债和政策性金融债",
          "url": "https://wallstreetcn.com/livenews/3084648",
          "source": "华尔街见闻-快讯",
          "ranks": [
            3,
            27
          ],
          "is_new": false,
          "appearance_count": 2,
          "time_info": "[08时08分 ~ 09时31分]"
        },
        {
          "title": "英国两年期国债收益率涨24个基点",
          "url": "https://wallstreetcn.com/livenews/3084474",
          "source": "华尔街见闻-快讯",
          "ranks": [
            8,
            28
          ],
          "is_new": false,
          "appearance_count": 2,
          "time_info": "[00时23分 ~ 01时22分]"
        },
        {
          "title": "美国财政部拍卖390亿美元10年期国债，得标利率4.282%（3月11日为4.217%），投标倍数2.43（前次为2.45）。",
          "url": "https://wallstreetcn.com/livenews/3084496",
          "source": "华尔街见闻-快讯",
          "ranks": [
            8,
            30
          ],
          "is_new": false,
          "appearance_count": 2,
          "time_info": "[01时22分 ~ 02时21分]"
        },
        {
          "title": "国债期货早盘收盘，30年期主力合约涨0.18%，10年期主力合约跌0.06%，5年期主力合约跌0.01%，2年期主力合约跌0.01%。",
          "url": "https://wallstreetcn.com/livenews/3084749",
          "source": "华尔街见闻-快讯",
          "ranks": [
            9,
            23
          ],
          "is_new": false,
          "appearance_count": 2,
          "time_info": "[12时00分 ~ 12时54分]"
        },
        {
          "title": "美联储3月会议纪要发布后，标普500指数涨幅维持在2.6%。 现货黄金维持0.8%的涨幅，持稳于北京时间06:32刷新的日低4713.94美元附近。 美国10年期国债收益率维持大约18个基点的跌幅，报4.2753%，01:00披露美债拍卖结果之后、在01:26回升至4.2832%刷新日高。 两年期美债收益率跌幅收窄至大约14个基点，刷新日高至3.7855%。 美元指数跌幅扩大至0.96%，测试98.900点。",
          "url": "https://wallstreetcn.com/livenews/3084524",
          "source": "华尔街见闻-快讯",
          "ranks": [
            18,
            27
          ],
          "is_new": false,
          "appearance_count": 2,
          "time_info": "[03时28分 ~ 04时10分]"
        },
        {
          "title": "日本五年期国债收益率上升2.0个基点，至1.805%。",
          "url": "https://flash.jin10.com/detail/20260409090123978800",
          "source": "金十数据",
          "ranks": [
            7
          ],
          "is_new": false,
          "appearance_count": 1,
          "time_info": "09时31分"
        },
        {
          "title": "Pimco据悉拟出售用于建设甲骨文数据中心的部分美债",
          "url": "https://wallstreetcn.com/livenews/3084872",
          "source": "华尔街见闻-快讯",
          "ranks": [
            7
          ],
          "is_new": false,
          "appearance_count": 1,
          "time_info": "15时29分"
        },
        {
          "title": "日本30年期国债收益率上行6个基点至3.655%。 日经225指数日内跌幅扩大至0.6%。",
          "url": "https://wallstreetcn.com/livenews/3084669",
          "source": "华尔街见闻-快讯",
          "ranks": [
            9
          ],
          "is_new": false,
          "appearance_count": 1,
          "time_info": "09时31分"
        },
        {
          "title": "日本五年期国债拍卖的认购倍数为3.58，前次拍卖该数值为3.69。",
          "url": "https://flash.jin10.com/detail/20260409113622687800",
          "source": "金十数据",
          "ranks": [
            10
          ],
          "is_new": false,
          "appearance_count": 1,
          "time_info": "12时00分"
        },
        {
          "title": "日本至4月3日当周买进外国债券 -24624亿日元，前值由-9454亿日元修正为-9455亿日元。",
          "url": "https://flash.jin10.com/detail/20260409075002671800",
          "source": "金十数据",
          "ranks": [
            12
          ],
          "is_new": false,
          "appearance_count": 1,
          "time_info": "08时08分"
        },
        {
          "title": "国债期货收盘，30年期主力合约涨0.09%，10年期主力合约跌0.00%，5年期主力合约涨0.03%，2年期主力合约涨0.02%。",
          "url": "https://wallstreetcn.com/livenews/3084867",
          "source": "华尔街见闻-快讯",
          "ranks": [
            12
          ],
          "is_new": false,
          "appearance_count": 1,
          "time_info": "15时29分"
        },
        {
          "title": "国债期货早盘收盘",
          "url": "https://flash.jin10.com/detail/20260409113230737800",
          "source": "金十数据",
          "ranks": [
            13
          ],
          "is_new": false,
          "appearance_count": 1,
          "time_info": "12时00分"
        },
        {
          "title": "意大利10年期国债收益率跌约27个基点，表现逊色于法西希三国",
          "url": "https://wallstreetcn.com/livenews/3084468",
          "source": "华尔街见闻-快讯",
          "ranks": [
            14
          ],
          "is_new": false,
          "appearance_count": 1,
          "time_info": "00时23分"
        },
        {
          "title": "日本30年期国债收益率上行4个基点至3.635%。 日本20年期国债收益率上行4.5个基点至3.310%。",
          "url": "https://wallstreetcn.com/livenews/3084662",
          "source": "华尔街见闻-快讯",
          "ranks": [
            14
          ],
          "is_new": false,
          "appearance_count": 1,
          "time_info": "09时31分"
        },
        {
          "title": "美国10年期国债收益率在拍卖后维持跌势，最新下跌6.2个基点，报4.281%。",
          "url": "https://flash.jin10.com/detail/20260409010625730800",
          "source": "金十数据",
          "ranks": [
            15
          ],
          "is_new": false,
          "appearance_count": 1,
          "time_info": "01时22分"
        },
        {
          "title": "印度10年期国债收益率上行5个基点至6.94%。",
          "url": "https://wallstreetcn.com/livenews/3084800",
          "source": "华尔街见闻-快讯",
          "ranks": [
            15
          ],
          "is_new": false,
          "appearance_count": 1,
          "time_info": "14时28分"
        },
        {
          "title": "日本30年期国债收益率上升4.0个基点，至3.635%。日本20年期国债收益率上升4.5个基点，至3.310%。",
          "url": "https://flash.jin10.com/detail/20260409085228434800",
          "source": "金十数据",
          "ranks": [
            16
          ],
          "is_new": false,
          "appearance_count": 1,
          "time_info": "09时31分"
        },
        {
          "title": "美债收益率于美联储会议纪要发布后转涨",
          "url": "https://wallstreetcn.com/livenews/3084556",
          "source": "华尔街见闻-快讯",
          "ranks": [
            17
          ],
          "is_new": false,
          "appearance_count": 1,
          "time_info": "05时13分"
        },
        {
          "title": "美国财政部拍卖四个月期国债，得标利率3.6%，投标倍数3.34%。",
          "url": "https://wallstreetcn.com/livenews/3084463",
          "source": "华尔街见闻-快讯",
          "ranks": [
            19
          ],
          "is_new": false,
          "appearance_count": 1,
          "time_info": "00时23分"
        },
        {
          "title": "日本10年期国债收益率上行1.5个基点至2.380%。",
          "url": "https://wallstreetcn.com/livenews/3084657",
          "source": "华尔街见闻-快讯",
          "ranks": [
            19
          ],
          "is_new": false,
          "appearance_count": 1,
          "time_info": "09时31分"
        },
        {
          "title": "美国至4月8日10年期国债竞拍-投标倍数 2.43，前值2.45。",
          "url": "https://flash.jin10.com/detail/20260409010203827800",
          "source": "金十数据",
          "ranks": [
            20
          ],
          "is_new": false,
          "appearance_count": 1,
          "time_info": "01时22分"
        },
        {
          "title": "美国至4月8日10年期国债竞拍-得标利率配置百分比 38.89%，前值24.68%。",
          "url": "https://flash.jin10.com/detail/20260409010203826800",
          "source": "金十数据",
          "ranks": [
            21
          ],
          "is_new": false,
          "appearance_count": 1,
          "time_info": "01时22分"
        },
        {
          "title": "美国至4月8日10年期国债竞拍-得标利率 4.282%，前值4.22%。",
          "url": "https://flash.jin10.com/detail/20260409010203821800",
          "source": "金十数据",
          "ranks": [
            22
          ],
          "is_new": false,
          "appearance_count": 1,
          "time_info": "01时22分"
        },
        {
          "title": "德国两年期国债收益率走高，最新上涨5.5个基点，报2.5484%。",
          "url": "https://flash.jin10.com/detail/20260409153811306800",
          "source": "金十数据",
          "ranks": [
            22
          ],
          "is_new": false,
          "appearance_count": 1,
          "time_info": "16时27分"
        },
        {
          "title": "国债期货开盘，30年期主力合约涨0.16%，10年期主力合约涨0.03%，5年期主力合约涨0.03%，2年期主力合约涨0.01%。",
          "url": "https://wallstreetcn.com/livenews/3084684",
          "source": "华尔街见闻-快讯",
          "ranks": [
            23
          ],
          "is_new": false,
          "appearance_count": 1,
          "time_info": "10时59分"
        },
        {
          "title": "德国2年期国债收益率上行，最新上行5.5个基点，报2.5484%。",
          "url": "https://wallstreetcn.com/livenews/3084894",
          "source": "华尔街见闻-快讯",
          "ranks": [
            25
          ],
          "is_new": false,
          "appearance_count": 1,
          "time_info": "16时27分"
        },
        {
          "title": "德国10年期国债收益率延续升势，上涨5个基点，报2.9941%。",
          "url": "https://flash.jin10.com/detail/20260409170135952800",
          "source": "金十数据",
          "ranks": [
            26
          ],
          "is_new": false,
          "appearance_count": 1,
          "time_info": "17时25分"
        }
      ]
    },
    {
      "keyword_group": "chatgpt openai",
      "match_count": 11,
      "titles": [
        {
          "title": "曝ChatGPT6本月发布",
          "url": "https://search.bilibili.com/all?keyword=%E6%9B%9DGPT6%E6%9C%AC%E6%9C%88%E5%8F%91%E5%B8%83",
          "source": "bilibili 热搜",
          "ranks": [
            20,
            19,
            21,
            22
          ],
          "is_new": false,
          "appearance_count": 11,
          "time_info": "[00时23分 ~ 09时31分]"
        },
        {
          "title": "OpenAI预计到2030年广告收入将达到1000亿美元，预计今年将产生25亿美元广告收入。（Axios）",
          "url": "https://wallstreetcn.com/livenews/3084981",
          "source": "华尔街见闻-快讯",
          "ranks": [
            4
          ],
          "is_new": true,
          "appearance_count": 1,
          "time_info": "18时23分"
        },
        {
          "title": "OpenAI因安全风险采取了分阶段推出新模型的策略。（Axios）",
          "url": "https://wallstreetcn.com/livenews/3084962",
          "source": "华尔街见闻-快讯",
          "ranks": [
            6,
            14
          ],
          "is_new": false,
          "appearance_count": 2,
          "time_info": "[17时25分 ~ 18时23分]"
        },
        {
          "title": "OpenAI：已暂停英国“星际之门”项目，将在“合适条件”下推进英国计划。",
          "url": "https://wallstreetcn.com/livenews/3084971",
          "source": "华尔街见闻-快讯",
          "ranks": [
            8
          ],
          "is_new": true,
          "appearance_count": 1,
          "time_info": "18时23分"
        },
        {
          "title": "OpenAI首席财务官表示，OpenAI正筹备上市，将向散户投资者分配IPO股份。",
          "url": "https://flash.jin10.com/detail/20260409051237886800",
          "source": "金十数据",
          "ranks": [
            11
          ],
          "is_new": false,
          "appearance_count": 1,
          "time_info": "06时11分"
        },
        {
          "title": "OpenAI拟分阶段推出新模型 以防范网络安全风险",
          "url": "https://flash.jin10.com/detail/20260409170850684800",
          "source": "金十数据",
          "ranks": [
            11
          ],
          "is_new": false,
          "appearance_count": 1,
          "time_info": "17时25分"
        },
        {
          "title": "据AXIOS网站：OpenAI计划分阶段推出新模型。",
          "url": "https://flash.jin10.com/detail/20260409170825979800",
          "source": "金十数据",
          "ranks": [
            12
          ],
          "is_new": false,
          "appearance_count": 1,
          "time_info": "17时25分"
        },
        {
          "title": "据AXIOS网站：OpenAI预计到2030年广告收入将达到1000亿美元。",
          "url": "https://flash.jin10.com/detail/20260409174337065800",
          "source": "金十数据",
          "ranks": [
            13
          ],
          "is_new": true,
          "appearance_count": 1,
          "time_info": "18时23分"
        },
        {
          "title": "OpenAI的CFO Sarah Friar：公司将在IPO中配售股票给散户们。（CNBC）",
          "url": "https://wallstreetcn.com/livenews/3084581",
          "source": "华尔街见闻-快讯",
          "ranks": [
            14
          ],
          "is_new": false,
          "appearance_count": 1,
          "time_info": "06时11分"
        },
        {
          "title": "据AXIOS网站：OpenAI预计今年广告收入达25亿美元。",
          "url": "https://flash.jin10.com/detail/20260409174200315800",
          "source": "金十数据",
          "ranks": [
            17
          ],
          "is_new": true,
          "appearance_count": 1,
          "time_info": "18时23分"
        },
        {
          "title": "OpenAI首席营收官：企业业务收入占比超过40%",
          "url": "https://flash.jin10.com/detail/20260409072451625800",
          "source": "金十数据",
          "ranks": [
            21
          ],
          "is_new": false,
          "appearance_count": 1,
          "time_info": "08时08分"
        }
      ]
    },
    {
      "keyword_group": "谷歌 google gemini",
      "match_count": 3,
      "titles": [
        {
          "title": "Meta发布自家第一款重磅AI大模型Muse Spark，试图追赶谷歌、OpenAI的脚步。",
          "url": "https://wallstreetcn.com/livenews/3084479",
          "source": "华尔街见闻-快讯",
          "ranks": [
            3
          ],
          "is_new": false,
          "appearance_count": 1,
          "time_info": "00时23分"
        },
        {
          "title": "谷歌(GOOG.O)：未来几周内，将向100多个国家推出谷歌财经，并提供全面的本地语言支持。",
          "url": "https://flash.jin10.com/detail/20260409000213022800",
          "source": "金十数据",
          "ranks": [
            20
          ],
          "is_new": false,
          "appearance_count": 1,
          "time_info": "00时23分"
        },
        {
          "title": "Meta发布新AI模型，力图追赶谷歌和OpenAI",
          "url": "https://wallstreetcn.com/livenews/3084479",
          "source": "华尔街见闻-快讯",
          "ranks": [
            23
          ],
          "is_new": false,
          "appearance_count": 1,
          "time_info": "01时22分"
        }
      ]
    },
    {
      "keyword_group": "美元",
      "match_count": 3,
      "titles": [
        {
          "title": "美元指数跌超0.7%",
          "url": "https://wallstreetcn.com/livenews/3084552",
          "source": "华尔街见闻-快讯",
          "ranks": [
            2,
            21
          ],
          "is_new": false,
          "appearance_count": 2,
          "time_info": "[04时10分 ~ 05时13分]"
        },
        {
          "title": "美元指数维持稳定 本次停火可能只是冲突中的一次暂停",
          "url": "https://flash.jin10.com/detail/20260409145433425800",
          "source": "金十数据",
          "ranks": [
            18
          ],
          "is_new": false,
          "appearance_count": 1,
          "time_info": "15时29分"
        },
        {
          "title": "美元指数8日大幅下跌",
          "url": "https://flash.jin10.com/detail/20260409041103837800",
          "source": "金十数据",
          "ranks": [
            24
          ],
          "is_new": false,
          "appearance_count": 1,
          "time_info": "05时13分"
        }
      ]
    },
    {
      "keyword_group": "金价 银价",
      "match_count": 2,
      "titles": [
        {
          "title": "金十图示：2026年04月09日（周四）上海金午盘价为1038.52元/克，较国际金价(1035.1元/克)，高3.42元/克",
          "url": "https://flash.jin10.com/detail/20260409150245696800",
          "source": "金十数据",
          "ranks": [
            5
          ],
          "is_new": false,
          "appearance_count": 1,
          "time_info": "15时29分"
        },
        {
          "title": "金价走势“先涨后疑”，市场又在重算什么？",
          "url": "https://flash.jin10.com/detail/20260409115543509800",
          "source": "金十数据",
          "ranks": [
            30
          ],
          "is_new": false,
          "appearance_count": 1,
          "time_info": "12时54分"
        }
      ]
    }
  ],
  "report_image_url": "https://joyce677.github.io/TrendRadar/img/news.jpg"
}